input/syntetic/design/spec1.v
/* Generated by Yosys 0.47+149 (git sha1 889894a6d, clang++ 18.1.8 -fPIC -O3) */

module spec1(clock, a_2_0, a_2_1, c_2_0);
  wire _00_;
  wire _01_;
  wire _02_;
  wire _03_;
  wire _04_;
  wire _05_;
  wire _06_;
  wire _07_;
  wire _08_;
  wire _09_;
  wire _10_;
  wire _11_;
  wire _12_;
  wire _13_;
  wire _14_;
  wire _15_;
  wire _16_;
  wire _17_;
  wire _18_;
  wire _19_;
  wire _20_;
  wire _21_;
  wire _22_;
  wire _23_;
  wire _24_;
  wire _25_;
  wire _26_;
  wire _27_;
  wire _28_;
  wire _29_;
  wire _30_;
  wire _31_;
  wire _32_;
  wire _33_;
  wire _34_;
  wire _35_;
  wire _36_;
  reg _37_ = 1'h0;
  input a_2_0;
  wire a_2_0;
  input a_2_1;
  wire a_2_1;
  output c_2_0;
  reg c_2_0 = 1'h0;
  input clock;
  wire clock;
  assign _00_ = _35_ & _36_;
  assign _02_ = a_2_0 & a_2_1;
  assign _03_ = _02_ & _36_;
  assign _05_ = _13_ & a_2_1;
  assign _06_ = _05_ & _36_;
  assign _08_ = _30_ & c_2_0;
  assign _09_ = _02_ & _08_;
  assign _11_ = _05_ & _08_;
  assign _14_ = _35_ & _08_;
  assign _16_ = _37_ & c_2_0;
  assign _17_ = a_2_0 & _16_;
  assign _19_ = _01_ & _07_;
  assign _20_ = _34_ & _19_;
  assign _21_ = _15_ & _18_;
  assign _22_ = _12_ & _21_;
  assign _23_ = _20_ & _22_;
  assign _26_ = _04_ & _07_;
  assign _27_ = _10_ & _12_;
  assign _28_ = _26_ & _27_;
  assign _32_ = _30_ & _31_;
  assign _33_ = a_2_0 & _32_;
  assign _35_ = a_2_0 & _25_;
  assign _36_ = _37_ & _31_;
  always @(posedge clock)
    _37_ <= _24_;
  always @(posedge clock)
    c_2_0 <= _29_;
  assign _13_ = ~a_2_0;
  assign _01_ = ~_00_;
  assign _04_ = ~_03_;
  assign _07_ = ~_06_;
  assign _10_ = ~_09_;
  assign _12_ = ~_11_;
  assign _25_ = ~a_2_1;
  assign _15_ = ~_14_;
  assign _18_ = ~_17_;
  assign _24_ = ~_23_;
  assign _30_ = ~_37_;
  assign _29_ = ~_28_;
  assign _31_ = ~c_2_0;
  assign _34_ = ~_33_;
endmodule

input/syntetic/design/spec0.v
/* Generated by Yosys 0.47+149 (git sha1 889894a6d, clang++ 18.1.8 -fPIC -O3) */

module spec0(clock, a_1_0, a_1_1, c_1_0);
  wire _00_;
  wire _01_;
  wire _02_;
  wire _03_;
  wire _04_;
  wire _05_;
  wire _06_;
  wire _07_;
  wire _08_;
  wire _09_;
  wire _10_;
  wire _11_;
  wire _12_;
  wire _13_;
  wire _14_;
  wire _15_;
  wire _16_;
  wire _17_;
  wire _18_;
  wire _19_;
  wire _20_;
  wire _21_;
  wire _22_;
  wire _23_;
  wire _24_;
  wire _25_;
  wire _26_;
  wire _27_;
  wire _28_;
  wire _29_;
  wire _30_;
  wire _31_;
  wire _32_;
  wire _33_;
  wire _34_;
  wire _35_;
  wire _36_;
  reg _37_ = 1'h0;
  input a_1_0;
  wire a_1_0;
  input a_1_1;
  wire a_1_1;
  output c_1_0;
  reg c_1_0 = 1'h0;
  input clock;
  wire clock;
  assign _00_ = _35_ & _36_;
  assign _02_ = a_1_0 & a_1_1;
  assign _03_ = _02_ & _36_;
  assign _05_ = _13_ & a_1_1;
  assign _06_ = _05_ & _36_;
  assign _08_ = _30_ & c_1_0;
  assign _09_ = _02_ & _08_;
  assign _11_ = _05_ & _08_;
  assign _14_ = _35_ & _08_;
  assign _16_ = _37_ & c_1_0;
  assign _17_ = a_1_0 & _16_;
  assign _19_ = _01_ & _07_;
  assign _20_ = _34_ & _19_;
  assign _21_ = _15_ & _18_;
  assign _22_ = _12_ & _21_;
  assign _23_ = _20_ & _22_;
  assign _26_ = _04_ & _07_;
  assign _27_ = _10_ & _12_;
  assign _28_ = _26_ & _27_;
  assign _32_ = _30_ & _31_;
  assign _33_ = a_1_0 & _32_;
  assign _35_ = a_1_0 & _25_;
  assign _36_ = _37_ & _31_;
  always @(posedge clock)
    _37_ <= _24_;
  always @(posedge clock)
    c_1_0 <= _29_;
  assign _13_ = ~a_1_0;
  assign _01_ = ~_00_;
  assign _04_ = ~_03_;
  assign _07_ = ~_06_;
  assign _10_ = ~_09_;
  assign _12_ = ~_11_;
  assign _25_ = ~a_1_1;
  assign _15_ = ~_14_;
  assign _18_ = ~_17_;
  assign _24_ = ~_23_;
  assign _30_ = ~_37_;
  assign _29_ = ~_28_;
  assign _31_ = ~c_1_0;
  assign _34_ = ~_33_;
endmodule

input/syntetic/design/test.v
module test(
clock,a_1_0,a_1_1,a_2_0,a_2_1,c_1_0,c_2_0);
input clock,a_1_0,a_1_1,a_2_0,a_2_1;
output c_1_0,c_2_0;
spec0 spec_sbm0(clock, a_1_0,a_1_1,c_1_0);
spec1 spec_sbm1(clock, a_2_0,a_2_1,c_2_0);
endmodule

input/syntetic/traces/trace.vcd
$version Generated by VerilatedVcd $end
$timescale 1ps $end
 $scope module TOP $end
  $var wire 1 # clock $end
  $var wire 1 $ a_1_0 $end
  $var wire 1 % a_1_1 $end
  $var wire 1 & a_2_0 $end
  $var wire 1 ' a_2_1 $end
  $var wire 1 ( c_1_0 $end
  $var wire 1 ) c_2_0 $end
  $scope module test $end
   $var wire 1 # clock $end
   $var wire 1 $ a_1_0 $end
   $var wire 1 % a_1_1 $end
   $var wire 1 & a_2_0 $end
   $var wire 1 ' a_2_1 $end
   $var wire 1 ( c_1_0 $end
   $var wire 1 ) c_2_0 $end
   $scope module spec_sbm0 $end
    $var wire 1 $ a_1_0 $end
    $var wire 1 % a_1_1 $end
    $var wire 1 ( c_1_0 $end
    $var wire 1 # clock $end
   $upscope $end
   $scope module spec_sbm1 $end
    $var wire 1 & a_2_0 $end
    $var wire 1 ' a_2_1 $end
    $var wire 1 ) c_2_0 $end
    $var wire 1 # clock $end
   $upscope $end
  $upscope $end
 $upscope $end
$enddefinitions $end


#0
1#
0$
0%
0&
0'
0(
0)
#1
0#
#2
1#
1%
1&
1'
#3
0#
1$
0%
0&
#4
1#
1%
1)
#5
0#
0%
1&
0'
#6
1#
0$
0&
0)
#7
0#
1%
1&
1'
#8
1#
0&
0'
#9
0#
1$
0%
1&
1'
#10
1#
0$
1%
0'
#11
0#
0%
1'
#12
1#
1$
1%
1)
#13
0#
0%
0&
0'
#14
1#
0$
1&
1'
#15
0#
1%
0&
#16
1#
0'
0)
#17
0#
1$
1'
#18
1#
0'
#19
0#
1'
#20
1#
0'
1(
#21
0#
0$
0%
1&
#22
1#
0&
1'
0(
#23
0#
1%
1&
0'
#24
1#
1$
0%
0&
#25
0#
0$
1&
#26
1#
1%
0&
1(
#27
0#
0%
1'
#28
1#
1$
1&
0(
#29
0#
0$
0&
#30
1#
1%
1(
1)
#31
0#
1$
#32
1#
1&
0'
0(
0)
#33
0#
1'
#34
1#
0%
1)
#35
0#
1%
0&
#36
1#
0%
1&
0'
0)
#37
0#
1%
0&
#38
1#
0%
1'
1)
#39
0#
1%
0'
#40
1#
1(
0)
#41
0#
1&
#42
1#
0$
0%
0&
1'
0(
#43
0#
1&
#44
1#
0&
0'
#45
0#
1%
1&
1'
#46
1#
1$
0%
#47
0#
0'
#48
1#
1%
0&
1'
1(
1)
#49
0#
1&
0'
#50
1#
0%
0&
1'
0(
0)
#51
0#
1%
#52
1#
0$
1&
0'
1(
#53
0#
0%
0&
1'
#54
1#
0'
0(
#55
0#
1$
1&
1'
#56
1#
1%
0&
0'
#57
0#
#58
1#
0$
1&
1(
#59
0#
0%
#60
1#
1%
0(
#61
0#
0&
1'
#62
1#
1&
0'
#63
0#
0%
0&
#64
1#
1%
1&
1'
1)
#65
0#
0&
#66
1#
0%
0'
0)
#67
0#
1$
#68
1#
0$
1%
#69
0#
0%
#70
1#
1$
1&
#71
0#
1%
#72
1#
0$
0%
1'
1)
#73
0#
1$
1%
0'
#74
1#
0$
1'
#75
0#
0&
#76
1#
0%
0'
0)
#77
0#
#78
1#
1$
1&
#79
0#
0$
1'
#80
1#
1%
0'
1(
#81
0#
0&
#82
1#
1$
0%
1&
0(
#83
0#
1%
1'
#84
1#
0$
1(
1)
#85
0#
1$
0%
0'
#86
1#
0$
0&
1'
0(
#87
0#
1%
0'
#88
1#
1$
0%
0)
#89
0#
0$
#90
1#
1$
1%
1'
1(
#91
0#
0$
0'
#92
1#
0%
0(
#93
0#
1$
1&
1'
#94
1#
0&
0'
#95
0#
1&
1'
#96
1#
0&
0'
#97
0#
0$
1%
1&
1'
#98
1#
1$
0&
1(
#99
0#
0$
#100
1#
0%
0'
0(
#101
0#
1$
#102
1#
#103
0#
0$
#104
1#
1%
1&
1'
1(
#105
0#
0%
0&
#106
1#
1%
0(
1)
#107
0#
0'
#108
1#
1&
1'
0)
#109
0#
1$
0%
#110
1#
0&
0'
#111
0#
0$
1%
1&
1'
#112
1#
0&
0'
1(
#113
0#
#114
1#
0%
0(
#115
0#
1$
1%
1&
#116
1#
0$
0&
1'
#117
0#
1$
0%
1&
0'
#118
1#
1'
#119
0#
0$
1%
#120
1#
1$
0%
0'
#121
0#
1%
1'
#122
1#
0$
0&
1(
1)
#123
0#
1$
0%
1&
#124
1#
0'
0(
0)
#125
0#
0$
0&
1'
#126
1#
1$
1)
#127
0#
0$
1%
#128
1#
1$
1&
1(
0)
#129
0#
0&
0'
#130
1#
0$
0%
1'
0(
1)
#131
0#
1$
0'
#132
1#
0$
1'
0)
#133
0#
0'
#134
1#
1%
#135
0#
0%
1&
#136
1#
1%
1'
#137
0#
1$
0%
0&
#138
1#
0'
#139
0#
1%
#140
1#
0$
1&
1'
1(
#141
0#
1$
0%
0'
#142
1#
0$
0&
0(
#143
0#
1$
#144
1#
1%
1&
1'
#145
0#
0$
#146
1#
1(
1)
#147
0#
1$
0%
#148
1#
0$
1%
0(
#149
0#
1$
0%
0&
0'
#150
1#
0$
1%
1'
#151
0#
1$
0%
1&
#152
1#
1%
0'
0)
#153
0#
0%
0&
1'
#154
1#
1&
1)
#155
0#
0$
1%
0&
0'
#156
1#
1$
1&
1'
1(
#157
0#
0'
#158
1#
0%
1'
0(
#159
0#
0$
1%
0&
0'
#160
1#
0%
1'
#161
0#
1$
#162
1#
0$
1%
0'
0)
#163
0#
#164
1#
1$
0%
1'
#165
0#
1%
1&
0'
#166
1#
0$
1'
1(
#167
0#
0%
0&
#168
1#
1$
1%
1&
0'
0(
#169
0#
0%
#170
1#
1'
1)
#171
0#
0$
#172
1#
0&
#173
0#
1&
#174
1#
1$
1%
0&
0'
0)
#175
0#
0$
1'
#176
1#
1$
1(
#177
0#
0%
0'
#178
1#
1%
#179
0#
1&
1'
#180
1#
0$
#181
0#
0%
0'
#182
1#
1$
0&
1'
0(
1)
#183
0#
0$
1%
1&
0'
#184
1#
1$
1'
1(
0)
#185
0#
0%
0'
#186
1#
0(
#187
0#
1'
#188
1#
0$
1%
1(
1)
#189
0#
1$
0%
0'
#190
1#
0&
0(
0)
#191
0#
0$
1'
#192
1#
1$
#193
0#
0'
#194
1#
0$
1'
#195
0#
1$
#196
1#
0$
1&
#197
0#
1%
0&
#198
1#
0'
#199
0#
0%
#200
1#
1%
1'
#201
0#
0%
1&
#202
1#
1%
0&
0'
#203
0#
1$
1&
1'
#204
1#
0$
0%
#205
0#
1$
1%
#206
1#
0%
0&
1)
#207
0#
0$
#208
1#
1&
0'
0)
#209
0#
1$
1%
0&
#210
1#
0%
1'
1)
#211
0#
0$
1%
1&
0'
#212
1#
1(
0)
#213
0#
0&
1'
#214
1#
1$
1&
0'
0(
#215
0#
0%
0&
1'
#216
1#
1%
1(
1)
#217
0#
0$
0'
#218
1#
1$
1'
0)
#219
0#
#220
1#
1&
0'
#221
0#
0%
0&
#222
1#
1&
0(
#223
0#
1%
0&
#224
1#
0$
1&
1'
1(
1)
#225
0#
1$
0%
0'
#226
1#
1%
0(
0)
#227
0#
0$
0%
#228
1#
1%
0&
1'
1(
1)
#229
0#
0%
1&
#230
1#
1$
0&
0'
0(
0)
#231
0#
0$
1%
#232
1#
1$
0%
1&
#233
0#
0$
1%
0&
#234
1#
1'
1(
1)
#235
0#
1$
0'
#236
1#
0$
1&
1'
0(
0)
#237
0#
0%
0'
#238
1#
1$
1'
1)
#239
0#
1%
#240
1#
0$
0%
0'
0)
#241
0#
1%
#242
1#
0%
#243
0#
1$
1%
1'
#244
1#
0$
0&
1)
#245
0#
1$
0%
#246
1#
1%
0'
0)
#247
0#
0$
0%
#248
1#
1$
1%
1(
#249
0#
0$
1'
#250
1#
1$
1&
0'
#251
0#
0&
#252
1#
0$
0%
1&
1'
0(
1)
#253
0#
1$
1%
#254
1#
0%
0&
0'
0)
#255
0#
0$
1'
#256
1#
1%
1&
0'
1(
#257
0#
1$
0%
#258
1#
0$
1%
0&
1'
0(
1)
#259
0#
1&
#260
1#
0%
0)
#261
0#
1%
0&
#262
1#
1&
0'
#263
0#
1$
1'
#264
1#
0$
0%
0&
1)
#265
0#
1$
1%
0'
#266
1#
0$
0)
#267
0#
1$
0%
1'
#268
1#
0$
#269
0#
1&
0'
#270
1#
0&
1'
#271
0#
1$
1%
1&
#272
1#
0%
0'
#273
0#
1%
1'
#274
1#
0&
0'
1(
#275
0#
0%
1&
1'
#276
1#
1%
#277
0#
0$
0&
0'
#278
1#
0%
1&
1'
0(
1)
#279
0#
1%
#280
1#
0%
#281
0#
0'
#282
1#
1%
0)
#283
0#
0%
1'
#284
1#
1%
1)
#285
0#
1$
0%
0&
#286
1#
1%
#287
0#
0$
#288
1#
0%
1&
0'
0)
#289
0#
1$
0&
#290
1#
1&
1'
1)
#291
0#
1%
0&
#292
1#
0%
#293
0#
#294
1#
1&
0'
0)
#295
0#
0$
1%
1'
#296
1#
0%
0&
0'
#297
0#
1&
1'
#298
1#
1%
0&
0'
#299
0#
1'
#300
1#
1$
1&
0'
#301
0#
0$
0%
#302
1#
1$
0&
1'
1)
#303
0#
1%
1&
#304
1#
0'
1(
0)
#305
0#
0$
0%
0&
#306
1#
1&
1'
0(
1)
#307
0#
1%
#308
1#
1$
0&
#309
0#
0%
1&
#310
1#
0$
1%
0&
0'
1(
0)
#311
0#
1$
1'
#312
1#
0$
1&
0(
#313
0#
1$
0'
#314
1#
0$
0%
0&
1'
1)
#315
0#
1$
1%
1&
0'
#316
1#
0&
0)
#317
0#
0$
1&
1'
#318
1#
1$
0'
1(
#319
0#
0%
1'
#320
1#
0$
0(
1)
#321
0#
#322
1#
1$
1%
0'
0)
#323
0#
0$
0&
1'
#324
1#
1$
1&
0'
1(
#325
0#
0$
0&
1'
#326
1#
1$
0'
#327
0#
0%
1&
1'
#328
1#
0$
0&
0(
#329
0#
1&
0'
#330
1#
1'
#331
0#
0&
0'
#332
1#
1$
1&
1'
1)
#333
0#
0$
1%
#334
1#
1$
0%
0&
#335
0#
1&
#336
1#
1%
1(
0)
#337
0#
0$
0&
#338
1#
1$
0%
1&
0'
0(
#339
0#
1'
#340
1#
0$
0&
0'
#341
0#
1$
1&
#342
1#
0$
0&
1'
#343
0#
1$
1%
#344
1#
0%
#345
0#
0$
1%
1&
#346
1#
1$
0&
0'
1(
#347
0#
#348
1#
0$
0%
1&
1'
0(
#349
0#
1%
0&
0'
#350
1#
0%
1&
#351
0#
1$
1%
#352
1#
0%
1'
1)
#353
0#
0&
0'
#354
1#
0$
1&
0)
#355
0#
1$
1'
#356
1#
0$
0&
0'
#357
0#
1%
1&
1'
#358
1#
#359
0#
0%
0&
#360
1#
1$
1&
0'
#361
0#
0&
#362
1#
1&
1'
1)
#363
0#
0$
1%
0&
#364
1#
1$
0%
1&
#365
0#
0$
#366
1#
1$
1%
0'
1(
0)
#367
0#
0&
1'
#368
1#
1&
1)
#369
0#
0&
0'
#370
1#
0%
1&
1'
0(
#371
0#
#372
1#
0$
0&
0'
0)
#373
0#
#374
1#
1&
1'
#375
0#
1$
0&
#376
1#
0'
#377
0#
0$
1&
1'
#378
1#
0&
#379
0#
1$
1&
0'
#380
1#
1%
0&
1'
#381
0#
0%
1&
#382
1#
0$
#383
0#
1$
0'
#384
1#
1%
#385
0#
0$
0%
1'
#386
1#
1$
1%
0&
1(
1)
#387
0#
1&
0'
#388
1#
0$
0%
0&
1'
0(
0)
#389
0#
1$
1&
#390
1#
0$
0&
0'
#391
0#
1$
1%
1'
#392
1#
1&
0'
#393
0#
0$
#394
1#
0%
0&
#395
0#
1$
1'
#396
1#
0$
1&
#397
0#
0&
0'
#398
1#
1$
1%
#399
0#
0$
#400
1#
1$
0%
#401
0#
0$
1&
#402
1#
1$
1%
0&
1(
#403
0#
0$
0%
#404
1#
1$
1%
1'
#405
0#
1&
#406
1#
0%
0&
0'
0(
#407
0#
0$
1%
1&
1'
#408
1#
0%
0'
#409
0#
0&
#410
1#
1&
1'
1)
#411
0#
1$
0&
#412
1#
0$
1%
1&
0'
0)
#413
0#
0&
1'
#414
1#
0%
1)
#415
0#
1$
1%
#416
1#
1&
0)
#417
0#
0'
#418
1#
0%
1'
1)
#419
0#
1%
0&
0'
#420
1#
1(
0)
#421
0#
0%
1&
1'
#422
1#
0(
#423
0#
0'
#424
1#
0$
#425
0#
1$
1%
0&
1'
#426
1#
0%
1&
0'
#427
0#
0$
1%
1'
#428
1#
0&
1(
1)
#429
0#
1$
0%
1&
#430
1#
0$
1%
0'
0(
0)
#431
0#
0%
1'
#432
1#
0&
1)
#433
0#
1%
1&
#434
1#
1$
0&
0'
0)
#435
0#
0%
1'
#436
1#
0$
1&
#437
0#
1$
0'
#438
1#
0$
1%
1'
1)
#439
0#
0'
#440
1#
1$
0%
0&
1'
#441
0#
0'
#442
1#
0$
1%
1&
1(
0)
#443
0#
1$
0&
1'
#444
1#
1&
0(
1)
#445
0#
0$
0%
0&
0'
#446
1#
1$
1%
1&
1(
0)
#447
0#
0$
0&
#448
1#
1&
1'
1)
#449
0#
1$
0%
0'
#450
1#
0$
1%
0&
1'
0(
#451
0#
#452
1#
1$
0%
0)
#453
0#
0$
0'
#454
1#
1$
1&
#455
0#
0$
1'
#456
1#
0&
0'
#457
0#
1$
1%
1&
#458
1#
0&
#459
0#
0$
0%
1'
#460
1#
1$
0'
#461
0#
0$
1%
1'
#462
1#
0%
1&
#463
0#
0'
#464
1#
1$
1%
1'
1)
#465
0#
0$
0%
0&
0'
#466
1#
1$
1'
#467
0#
0$
1%
#468
1#
1$
1&
1(
0)
#469
0#
0$
0&
#470
1#
0%
1&
0'
0(
#471
0#
1%
0&
#472
1#
1$
0%
1'
1)
#473
0#
#474
1#
0$
1%
0'
1(
0)
#475
0#
1$
0%
1&
1'
#476
1#
0$
1%
0'
0(
#477
0#
0%
0&
#478
1#
#479
0#
1$
#480
1#
0$
#481
0#
1%
1'
#482
1#
1$
0%
1&
#483
0#
0$
0&
0'
#484
1#
1%
1&
1(
#485
0#
0%
#486
1#
0&
0(
#487
0#
1%
1'
#488
1#
0%
1&
#489
0#
0&
#490
1#
1$
1%
1)
#491
0#
0$
1&
#492
1#
0%
0&
0'
0)
#493
0#
#494
1#
1$
1%
1&
#495
0#
0%
0&
1'
#496
1#
0$
1%
1&
0'
1(
#497
0#
1$
#498
1#
0&
0(
#499
0#
0%
1'
#500
1#
#501
0#
1%
#502
1#
0'
1(
#503
0#
0$
1'
#504
1#
1$
0%
0'
0(
#505
0#
1&
#506
1#
1%
1(
#507
0#
0%
#508
1#
0$
1%
0&
#509
0#
1'
#510
1#
0'
0(
#511
0#
1'
#512
1#
#513
0#
1$
1&
#514
1#
0$
0&
#515
0#
0%
1&
0'
#516
1#
1$
1%
0&
#517
0#
0$
0%
#518
1#
1&
1'
#519
0#
1$
#520
1#
0&
1)
#521
0#
1&
#522
1#
0'
0)
#523
0#
1%
0&
1'
#524
1#
0$
0%
0'
#525
0#
1'
#526
1#
1$
#527
0#
1%
0'
#528
1#
0$
0%
1&
1'
#529
0#
0&
0'
#530
1#
1$
1%
#531
0#
0$
1&
#532
1#
1$
0%
1'
#533
0#
0$
1%
0&
0'
#534
1#
0%
1&
1'
1)
#535
0#
1$
#536
1#
0&
0'
0)
#537
0#
0$
1%
1'
#538
1#
0%
1&
0'
#539
0#
1%
#540
1#
1$
1'
1)
#541
0#
0%
0&
#542
1#
1%
1(
#543
0#
0$
1&
#544
1#
0%
0(
0)
#545
0#
1$
0&
0'
#546
1#
1%
1&
1'
1)
#547
0#
0$
0%
#548
1#
0&
#549
0#
1%
1&
0'
#550
1#
1$
0&
0)
#551
0#
0$
0%
1'
#552
1#
1$
1&
0'
#553
0#
1%
#554
1#
0$
0&
1(
#555
0#
1$
0%
1&
#556
1#
0&
0(
#557
0#
1&
#558
1#
0$
1'
#559
0#
1$
0'
#560
1#
0$
0&
#561
0#
1$
1%
1&
1'
#562
1#
0%
0&
#563
0#
1%
#564
1#
0$
1&
1(
#565
0#
0'
#566
1#
0%
0(
#567
0#
1%
0&
1'
#568
1#
1$
1&
0'
#569
0#
0$
0%
0&
#570
1#
1'
1)
#571
0#
1%
1&
0'
#572
1#
0%
0&
0)
#573
0#
1$
1%
1&
1'
#574
1#
0%
0&
#575
0#
0$
1&
#576
1#
#577
0#
1%
0&
0'
#578
1#
0%
#579
0#
1$
1&
#580
1#
1%
#581
0#
0$
0&
#582
1#
1&
1'
1(
1)
#583
0#
0%
#584
1#
0&
0'
0(
0)
#585
0#
1%
#586
1#
0%
1&
#587
0#
1$
1%
1'
#588
1#
0$
0&
0'
#589
0#
1$
0%
#590
1#
0$
1&
1'
#591
0#
1%
0'
#592
1#
1$
#593
0#
0%
0&
#594
1#
1%
1&
1'
1(
1)
#595
0#
0$
0&
0'
#596
1#
1$
0%
0(
0)
#597
0#
0$
1%
#598
1#
1$
1(
#599
0#
0%
1'
#600
1#
1&
0'
0(
#601
0#
1'
#602
1#
0$
1%
0'
1(
#603
0#
0%
0&
#604
1#
1%
1'
0(
1)
#605
0#
1$
0'
#606
1#
0$
0%
0)
#607
0#
1'
#608
1#
1$
#609
0#
1&
0'
#610
1#
0$
1%
1'
1(
#611
0#
1$
0'
#612
1#
0$
0%
0&
1'
0(
1)
#613
0#
1$
1%
1&
#614
1#
0)
#615
0#
0%
#616
1#
0'
#617
0#
0$
1'
#618
1#
1%
0&
0'
1(
#619
0#
1$
#620
1#
0%
1&
1'
0(
#621
0#
0$
1%
0&
0'
#622
1#
1$
0%
1'
1)
#623
0#
1%
1&
#624
1#
0$
0%
0&
0)
#625
0#
1$
0'
#626
1#
0$
1%
1&
1'
#627
0#
0'
#628
1#
0&
1'
1)
#629
0#
0%
#630
1#
1$
1&
0)
#631
0#
0$
1%
0&
0'
#632
1#
0%
1&
#633
0#
0&
1'
#634
1#
0'
#635
0#
1$
1%
#636
1#
0$
0%
1'
#637
0#
1%
1&
0'
#638
1#
0%
0&
1'
#639
0#
1&
0'
#640
1#
1$
1%
0&
#641
0#
0$
1&
1'
#642
1#
1$
0%
0&
0'
#643
0#
0$
1&
#644
1#
1$
0&
#645
0#
1%
1&
#646
1#
1'
1(
#647
0#
#648
1#
0&
0'
#649
0#
0$
0%
#650
1#
1&
1'
0(
#651
0#
0&
0'
#652
1#
#653
0#
1%
1&
#654
1#
1$
1'
#655
0#
0$
0%
0&
0'
#656
1#
1$
1&
#657
0#
0&
1'
#658
1#
0'
#659
0#
0$
1&
#660
1#
1$
1%
0&
1'
1(
#661
0#
#662
1#
0%
0'
0(
#663
0#
0$
#664
1#
1$
1'
#665
0#
0$
1%
1&
#666
1#
1$
0%
0'
#667
0#
0$
1%
0&
#668
1#
1(
#669
0#
0%
1'
#670
1#
0'
0(
#671
0#
1$
1'
#672
1#
0$
1%
1&
0'
#673
0#
0%
0&
#674
1#
1%
1'
1)
#675
0#
0%
0'
#676
1#
0)
#677
0#
1%
1'
#678
1#
0%
1&
#679
0#
1$
0&
#680
1#
1%
1&
1)
#681
0#
0$
0&
#682
1#
0%
0'
0)
#683
0#
1$
1%
1&
1'
#684
1#
0%
#685
0#
#686
1#
0$
1%
0&
0'
1(
#687
0#
1$
0%
1&
1'
#688
1#
0&
0'
0(
#689
0#
0$
1%
1&
1'
#690
1#
1$
0'
1(
#691
0#
0$
0%
#692
1#
1%
0&
1'
1)
#693
0#
0%
1&
0'
#694
1#
0(
0)
#695
0#
1$
1%
0&
1'
#696
1#
0$
1&
0'
#697
0#
0&
#698
1#
1$
0%
#699
0#
1%
#700
1#
0%
#701
0#
0$
1%
1'
#702
1#
1$
1&
0'
1(
#703
0#
0$
0%
0&
#704
1#
1%
1&
#705
0#
1$
0%
0&
#706
1#
0$
1%
1&
1'
0(
1)
#707
0#
1$
0%
0&
0'
#708
1#
1%
0)
#709
0#
0$
1&
1'
#710
1#
0%
0&
#711
0#
1%
0'
#712
1#
#713
0#
0%
1&
1'
#714
1#
0'
#715
0#
0&
#716
1#
1'
1)
#717
0#
1$
1&
0'
#718
1#
0&
1'
0)
#719
0#
0$
1&
#720
1#
1$
0'
#721
0#
0$
1%
0&
1'
#722
1#
1(
1)
#723
0#
1&
0'
#724
1#
1$
1'
0(
0)
#725
0#
0$
0%
0'
#726
1#
1$
0&
1'
1)
#727
0#
0'
#728
1#
1%
1(
0)
#729
0#
#730
1#
0$
1'
#731
0#
1$
0%
#732
1#
1%
1&
0(
#733
0#
0%
#734
1#
0&
0'
#735
0#
1&
#736
1#
#737
0#
0$
1%
#738
1#
1$
0&
1(
#739
0#
0$
0%
1&
1'
#740
1#
1$
0(
#741
0#
0&
0'
#742
1#
1%
1&
1(
#743
0#
0$
0%
#744
1#
1$
1'
0(
1)
#745
0#
0$
1%
#746
1#
0'
1(
0)
#747
0#
0%
#748
1#
1%
0&
1'
0(
1)
#749
0#
1$
0%
#750
1#
1&
0'
0)
#751
0#
0$
0&
1'
#752
1#
1$
1)
#753
0#
0$
0'
#754
1#
1$
1&
0)
#755
0#
0$
1%
0&
1'
#756
1#
1$
0%
0'
#757
0#
0$
#758
1#
1$
1'
#759
0#
0$
1%
1&
#760
1#
1$
0%
0'
#761
0#
1%
0&
1'
#762
1#
0%
0'
#763
0#
0$
1%
1&
1'
#764
1#
1$
1(
#765
0#
0'
#766
1#
0%
0&
0(
#767
0#
1&
#768
1#
0$
0&
#769
0#
1&
#770
1#
1$
0&
1'
#771
0#
1%
1&
0'
#772
1#
1'
1(
#773
0#
0$
0&
0'
#774
1#
0%
1&
0(
#775
0#
0&
1'
#776
1#
0'
#777
0#
1$
1%
1&
#778
1#
1'
#779
0#
0$
0%
0&
#780
1#
1$
1&
1)
#781
0#
0'
#782
1#
0$
1%
0&
1(
0)
#783
0#
0%
1&
#784
1#
1$
0(
#785
0#
0$
1'
#786
1#
1)
#787
0#
1$
0&
0'
#788
1#
1%
1'
#789
0#
1&
#790
1#
0&
1(
0)
#791
0#
0$
1&
#792
1#
0%
0(
#793
0#
0&
0'
#794
1#
1$
#795
0#
1'
#796
1#
0$
1%
1&
0'
1(
#797
0#
0%
0&
1'
#798
1#
1$
1&
0(
1)
#799
0#
#800
1#
0$
#801
0#
1$
0&
0'
#802
1#
0$
1'
#803
0#
1$
#804
1#
1%
1&
0)
#805
0#
0$
0%
#806
1#
1$
0&
1)
#807
0#
1%
0'
#808
1#
1&
1'
1(
0)
#809
0#
0%
#810
1#
1%
0&
0'
#811
0#
0$
0%
1&
#812
1#
1$
1'
0(
#813
0#
0$
0&
#814
1#
1%
1(
1)
#815
0#
0%
1&
#816
1#
1%
0'
0(
0)
#817
0#
0%
#818
1#
1$
1'
1)
#819
0#
0&
#820
1#
1%
0'
1(
0)
#821
0#
0$
1&
1'
#822
1#
1$
0&
0'
#823
0#
1&
1'
#824
1#
0$
0%
0&
0'
0(
#825
0#
1$
1%
#826
1#
1&
#827
0#
0%
#828
1#
#829
0#
0$
1%
1'
#830
1#
1$
0&
1(
1)
#831
0#
#832
1#
1&
0)
#833
0#
0'
#834
1#
0$
0&
#835
0#
0%
1&
#836
1#
1$
1%
0&
1'
0(
#837
0#
#838
1#
0%
#839
0#
0$
1&
0'
#840
1#
1'
#841
0#
1%
#842
1#
1$
0&
1)
#843
0#
0$
1&
#844
1#
0%
0&
0)
#845
0#
1&
#846
1#
1$
0&
#847
0#
1%
0'
#848
1#
0%
1&
1'
#849
0#
0$
1%
0&
0'
#850
1#
1(
#851
0#
1$
#852
1#
0$
1'
0(
#853
0#
1$
0%
1&
#854
1#
0$
1%
0&
#855
0#
#856
1#
0%
1&
0'
#857
0#
1$
#858
1#
0&
#859
0#
0$
#860
1#
1&
1'
#861
0#
0&
#862
1#
1$
1&
0'
#863
0#
0$
1%
1'
#864
1#
0%
0'
#865
0#
#866
1#
1$
0&
1'
1)
#867
0#
0$
#868
1#
1$
0'
0)
#869
0#
1'
#870
1#
0$
1%
0'
1(
#871
0#
1$
0%
1&
#872
1#
0$
1%
0&
1'
0(
#873
0#
1$
0%
1&
#874
1#
0$
0&
0'
#875
0#
1%
#876
1#
1$
1&
1'
#877
0#
0%
0'
#878
1#
1%
1'
1(
1)
#879
0#
0$
0'
#880
1#
0%
1'
0(
#881
0#
0&
#882
1#
1$
1%
0'
0)
#883
0#
0$
1'
#884
1#
1$
1(
#885
0#
0%
1&
0'
#886
1#
0(
#887
0#
1'
#888
1#
0$
0&
1)
#889
0#
1$
1%
#890
1#
0$
0'
0)
#891
0#
0%
1'
#892
1#
#893
0#
1$
1%
#894
1#
0%
1&
0'
#895
0#
1%
0&
#896
1#
0%
1'
1)
#897
0#
0$
0'
#898
1#
1&
1'
0)
#899
0#
0&
#900
1#
0'
#901
0#
1&
#902
1#
1$
0&
#903
0#
1%
#904
1#
0$
0%
#905
0#
1%
