input/syntetic/design/spec1.v
/* Generated by Yosys 0.47+149 (git sha1 889894a6d, clang++ 18.1.8 -fPIC -O3) */

module spec1(clock, a_2_0, a_2_1, c_2_0);
  wire _00_;
  wire _01_;
  wire _02_;
  wire _03_;
  wire _04_;
  wire _05_;
  wire _06_;
  wire _07_;
  wire _08_;
  wire _09_;
  wire _10_;
  wire _11_;
  wire _12_;
  wire _13_;
  wire _14_;
  wire _15_;
  wire _16_;
  wire _17_;
  wire _18_;
  wire _19_;
  wire _20_;
  wire _21_;
  wire _22_;
  wire _23_;
  wire _24_;
  wire _25_;
  wire _26_;
  wire _27_;
  wire _28_;
  wire _29_;
  wire _30_;
  wire _31_;
  wire _32_;
  wire _33_;
  wire _34_;
  wire _35_;
  wire _36_;
  reg _37_ = 1'h0;
  input a_2_0;
  wire a_2_0;
  input a_2_1;
  wire a_2_1;
  output c_2_0;
  reg c_2_0 = 1'h0;
  input clock;
  wire clock;
  assign _00_ = _35_ & _36_;
  assign _02_ = a_2_0 & a_2_1;
  assign _03_ = _02_ & _36_;
  assign _05_ = _13_ & a_2_1;
  assign _06_ = _05_ & _36_;
  assign _08_ = _30_ & c_2_0;
  assign _09_ = _02_ & _08_;
  assign _11_ = _05_ & _08_;
  assign _14_ = _35_ & _08_;
  assign _16_ = _37_ & c_2_0;
  assign _17_ = a_2_0 & _16_;
  assign _19_ = _01_ & _07_;
  assign _20_ = _34_ & _19_;
  assign _21_ = _15_ & _18_;
  assign _22_ = _12_ & _21_;
  assign _23_ = _20_ & _22_;
  assign _26_ = _04_ & _07_;
  assign _27_ = _10_ & _12_;
  assign _28_ = _26_ & _27_;
  assign _32_ = _30_ & _31_;
  assign _33_ = a_2_0 & _32_;
  assign _35_ = a_2_0 & _25_;
  assign _36_ = _37_ & _31_;
  always @(posedge clock)
    _37_ <= _24_;
  always @(posedge clock)
    c_2_0 <= _29_;
  assign _13_ = ~a_2_0;
  assign _01_ = ~_00_;
  assign _04_ = ~_03_;
  assign _07_ = ~_06_;
  assign _10_ = ~_09_;
  assign _12_ = ~_11_;
  assign _25_ = ~a_2_1;
  assign _15_ = ~_14_;
  assign _18_ = ~_17_;
  assign _24_ = ~_23_;
  assign _30_ = ~_37_;
  assign _29_ = ~_28_;
  assign _31_ = ~c_2_0;
  assign _34_ = ~_33_;
endmodule

input/syntetic/design/spec0.v
/* Generated by Yosys 0.47+149 (git sha1 889894a6d, clang++ 18.1.8 -fPIC -O3) */

module spec0(clock, a_1, b_1, c_1, d_1, e_1);
  wire _000_;
  wire _001_;
  wire _002_;
  wire _003_;
  wire _004_;
  wire _005_;
  wire _006_;
  wire _007_;
  wire _008_;
  wire _009_;
  wire _010_;
  wire _011_;
  wire _012_;
  wire _013_;
  wire _014_;
  wire _015_;
  wire _016_;
  wire _017_;
  wire _018_;
  wire _019_;
  wire _020_;
  wire _021_;
  wire _022_;
  wire _023_;
  wire _024_;
  wire _025_;
  wire _026_;
  wire _027_;
  wire _028_;
  wire _029_;
  wire _030_;
  wire _031_;
  wire _032_;
  wire _033_;
  wire _034_;
  wire _035_;
  wire _036_;
  wire _037_;
  wire _038_;
  wire _039_;
  wire _040_;
  wire _041_;
  wire _042_;
  wire _043_;
  wire _044_;
  wire _045_;
  wire _046_;
  wire _047_;
  wire _048_;
  wire _049_;
  wire _050_;
  wire _051_;
  wire _052_;
  wire _053_;
  wire _054_;
  wire _055_;
  wire _056_;
  wire _057_;
  wire _058_;
  wire _059_;
  wire _060_;
  wire _061_;
  wire _062_;
  wire _063_;
  wire _064_;
  wire _065_;
  wire _066_;
  wire _067_;
  wire _068_;
  wire _069_;
  wire _070_;
  wire _071_;
  wire _072_;
  wire _073_;
  wire _074_;
  wire _075_;
  wire _076_;
  wire _077_;
  wire _078_;
  wire _079_;
  wire _080_;
  wire _081_;
  wire _082_;
  wire _083_;
  wire _084_;
  wire _085_;
  wire _086_;
  wire _087_;
  wire _088_;
  wire _089_;
  wire _090_;
  wire _091_;
  wire _092_;
  wire _093_;
  wire _094_;
  wire _095_;
  wire _096_;
  wire _097_;
  wire _098_;
  wire _099_;
  wire _100_;
  wire _101_;
  wire _102_;
  wire _103_;
  wire _104_;
  wire _105_;
  wire _106_;
  wire _107_;
  wire _108_;
  wire _109_;
  wire _110_;
  wire _111_;
  wire _112_;
  wire _113_;
  wire _114_;
  wire _115_;
  wire _116_;
  wire _117_;
  wire _118_;
  wire _119_;
  wire _120_;
  wire _121_;
  wire _122_;
  wire _123_;
  wire _124_;
  wire _125_;
  wire _126_;
  wire _127_;
  wire _128_;
  wire _129_;
  wire _130_;
  wire _131_;
  wire _132_;
  wire _133_;
  wire _134_;
  wire _135_;
  wire _136_;
  wire _137_;
  wire _138_;
  wire _139_;
  wire _140_;
  wire _141_;
  wire _142_;
  wire _143_;
  wire _144_;
  wire _145_;
  wire _146_;
  wire _147_;
  wire _148_;
  wire _149_;
  wire _150_;
  wire _151_;
  wire _152_;
  wire _153_;
  wire _154_;
  wire _155_;
  wire _156_;
  wire _157_;
  wire _158_;
  wire _159_;
  wire _160_;
  wire _161_;
  wire _162_;
  wire _163_;
  wire _164_;
  wire _165_;
  wire _166_;
  wire _167_;
  wire _168_;
  wire _169_;
  wire _170_;
  wire _171_;
  wire _172_;
  wire _173_;
  wire _174_;
  wire _175_;
  wire _176_;
  wire _177_;
  wire _178_;
  wire _179_;
  wire _180_;
  wire _181_;
  wire _182_;
  wire _183_;
  wire _184_;
  wire _185_;
  wire _186_;
  wire _187_;
  wire _188_;
  wire _189_;
  wire _190_;
  wire _191_;
  wire _192_;
  wire _193_;
  wire _194_;
  wire _195_;
  wire _196_;
  wire _197_;
  wire _198_;
  wire _199_;
  wire _200_;
  wire _201_;
  wire _202_;
  wire _203_;
  wire _204_;
  wire _205_;
  wire _206_;
  wire _207_;
  wire _208_;
  wire _209_;
  wire _210_;
  wire _211_;
  wire _212_;
  wire _213_;
  wire _214_;
  wire _215_;
  wire _216_;
  wire _217_;
  wire _218_;
  wire _219_;
  wire _220_;
  wire _221_;
  wire _222_;
  wire _223_;
  wire _224_;
  wire _225_;
  wire _226_;
  wire _227_;
  wire _228_;
  wire _229_;
  wire _230_;
  wire _231_;
  wire _232_;
  wire _233_;
  wire _234_;
  wire _235_;
  wire _236_;
  wire _237_;
  wire _238_;
  wire _239_;
  wire _240_;
  wire _241_;
  wire _242_;
  wire _243_;
  wire _244_;
  wire _245_;
  wire _246_;
  wire _247_;
  wire _248_;
  reg _249_ = 1'h0;
  reg _250_ = 1'h0;
  reg _251_ = 1'h0;
  reg _252_ = 1'h0;
  input a_1;
  wire a_1;
  input b_1;
  wire b_1;
  output c_1;
  wire c_1;
  input clock;
  wire clock;
  output d_1;
  wire d_1;
  output e_1;
  wire e_1;
  assign _000_ = _204_ & _238_;
  assign _001_ = _208_ & _248_;
  assign _002_ = _226_ & _230_;
  assign _003_ = _221_ & _002_;
  assign _004_ = _001_ & _003_;
  assign _005_ = _247_ & _004_;
  assign _006_ = _242_ & _005_;
  assign _008_ = _118_ & _121_;
  assign _009_ = _137_ & _148_;
  assign _010_ = _134_ & _009_;
  assign _011_ = _008_ & _010_;
  assign _013_ = _150_ & _156_;
  assign _014_ = _161_ & _163_;
  assign _015_ = _158_ & _014_;
  assign _016_ = _013_ & _015_;
  assign _017_ = _011_ & _016_;
  assign _018_ = _176_ & _178_;
  assign _019_ = _196_ & _210_;
  assign _020_ = _194_ & _019_;
  assign _021_ = _018_ & _020_;
  assign _022_ = _212_ & _214_;
  assign _023_ = _219_ & _221_;
  assign _024_ = _216_ & _023_;
  assign _025_ = _022_ & _024_;
  assign _026_ = _021_ & _025_;
  assign _027_ = _017_ & _026_;
  assign _029_ = _129_ & _140_;
  assign _030_ = _126_ & _029_;
  assign _031_ = _143_ & _148_;
  assign _032_ = _031_ & _013_;
  assign _033_ = _030_ & _032_;
  assign _034_ = _131_ & _249_;
  assign _035_ = _180_ & _182_;
  assign _036_ = _158_ & _035_;
  assign _037_ = _184_ & _187_;
  assign _038_ = _190_ & _192_;
  assign _039_ = _037_ & _038_;
  assign _040_ = _036_ & _039_;
  assign _041_ = _033_ & _040_;
  assign _042_ = _196_ & _198_;
  assign _043_ = _194_ & _042_;
  assign _044_ = _200_ & _210_;
  assign _045_ = a_1 & _034_;
  assign _046_ = _044_ & _022_;
  assign _047_ = _043_ & _046_;
  assign _048_ = _223_ & _226_;
  assign _049_ = _228_ & _230_;
  assign _050_ = _048_ & _049_;
  assign _051_ = _024_ & _050_;
  assign _052_ = _047_ & _051_;
  assign _053_ = _041_ & _052_;
  assign _055_ = _134_ & _137_;
  assign _056_ = _154_ & _176_;
  assign _057_ = _045_ & _238_;
  assign _058_ = _152_ & _056_;
  assign _059_ = _055_ & _058_;
  assign _060_ = _178_ & _190_;
  assign _061_ = _194_ & _196_;
  assign _062_ = _192_ & _061_;
  assign _063_ = _060_ & _062_;
  assign _064_ = _059_ & _063_;
  assign _065_ = _198_ & _200_;
  assign _066_ = _208_ & _219_;
  assign _067_ = _206_ & _066_;
  assign _069_ = _065_ & _067_;
  assign _070_ = _221_ & _223_;
  assign _071_ = _226_ & _049_;
  assign _072_ = _070_ & _071_;
  assign _073_ = _069_ & _072_;
  assign _074_ = _064_ & _073_;
  assign _076_ = _129_ & _134_;
  assign _077_ = _126_ & _076_;
  assign _078_ = _140_ & _143_;
  assign _079_ = _137_ & _078_;
  assign _080_ = _077_ & _079_;
  assign _081_ = _178_ & _180_;
  assign _082_ = _176_ & _081_;
  assign _083_ = _182_ & _037_;
  assign _084_ = _082_ & _083_;
  assign _085_ = _080_ & _084_;
  assign _086_ = _192_ & _194_;
  assign _087_ = _190_ & _086_;
  assign _088_ = _196_ & _065_;
  assign _089_ = _087_ & _088_;
  assign _090_ = b_1 & _249_;
  assign _091_ = _219_ & _070_;
  assign _092_ = _091_ & _071_;
  assign _093_ = _089_ & _092_;
  assign _094_ = _085_ & _093_;
  assign _095_ = _150_ & _152_;
  assign _096_ = _148_ & _095_;
  assign _097_ = _156_ & _158_;
  assign _098_ = _154_ & _097_;
  assign _099_ = _096_ & _098_;
  assign _100_ = _099_ & _089_;
  assign _101_ = a_1 & _090_;
  assign _102_ = _208_ & _210_;
  assign _103_ = _206_ & _102_;
  assign _104_ = _214_ & _216_;
  assign _105_ = _212_ & _104_;
  assign _106_ = _103_ & _105_;
  assign _107_ = _106_ & _092_;
  assign _108_ = _100_ & _107_;
  assign _109_ = _163_ & _165_;
  assign _110_ = _161_ & _109_;
  assign _111_ = _170_ & _172_;
  assign _113_ = _101_ & _238_;
  assign _114_ = _168_ & _111_;
  assign _115_ = _110_ & _114_;
  assign _116_ = _115_ & _084_;
  assign _117_ = _116_ & _107_;
  assign _119_ = _112_ & _090_;
  assign _120_ = _119_ & _238_;
  assign _122_ = _131_ & _146_;
  assign _123_ = a_1 & _122_;
  assign _124_ = _250_ & _224_;
  assign _125_ = _123_ & _124_;
  assign _127_ = _112_ & _122_;
  assign _128_ = _127_ & _124_;
  assign _130_ = b_1 & _146_;
  assign _132_ = a_1 & _130_;
  assign _133_ = _132_ & _124_;
  assign _135_ = _112_ & _130_;
  assign _136_ = _135_ & _124_;
  assign _138_ = a_1 & _249_;
  assign _139_ = _138_ & _124_;
  assign _141_ = _112_ & _249_;
  assign _142_ = _141_ & _124_;
  assign _144_ = _251_ & _203_;
  assign _145_ = _166_ & _144_;
  assign _147_ = _123_ & _145_;
  assign _149_ = _127_ & _145_;
  assign _151_ = _132_ & _145_;
  assign _153_ = _135_ & _145_;
  assign _155_ = _138_ & _145_;
  assign _157_ = _141_ & _145_;
  assign _159_ = _250_ & _144_;
  assign _160_ = _132_ & _159_;
  assign _162_ = _135_ & _159_;
  assign _164_ = _123_ & _159_;
  assign _167_ = _127_ & _159_;
  assign _169_ = _138_ & _159_;
  assign _171_ = _141_ & _159_;
  assign _173_ = _185_ & _252_;
  assign _174_ = _166_ & _173_;
  assign _175_ = _132_ & _174_;
  assign _177_ = _135_ & _174_;
  assign _179_ = _123_ & _174_;
  assign _181_ = _127_ & _174_;
  assign _183_ = _138_ & _174_;
  assign _186_ = _141_ & _174_;
  assign _188_ = _250_ & _173_;
  assign _189_ = _123_ & _188_;
  assign _191_ = _127_ & _188_;
  assign _193_ = _132_ & _188_;
  assign _195_ = _135_ & _188_;
  assign _197_ = _138_ & _188_;
  assign _199_ = _141_ & _188_;
  assign _201_ = _251_ & _252_;
  assign _202_ = _166_ & _201_;
  assign _204_ = a_1 & _146_;
  assign _205_ = _132_ & _202_;
  assign _207_ = _135_ & _202_;
  assign _209_ = _123_ & _202_;
  assign _211_ = _127_ & _202_;
  assign _213_ = _138_ & _202_;
  assign _215_ = _141_ & _202_;
  assign _217_ = _250_ & _201_;
  assign _218_ = _132_ & _217_;
  assign _220_ = _135_ & _217_;
  assign _222_ = _123_ & _217_;
  assign _224_ = _185_ & _203_;
  assign _225_ = _127_ & _217_;
  assign _227_ = _138_ & _217_;
  assign _229_ = _141_ & _217_;
  assign _231_ = _068_ & _121_;
  assign _232_ = _012_ & _231_;
  assign _233_ = _137_ & _143_;
  assign _234_ = _129_ & _233_;
  assign _235_ = _232_ & _234_;
  assign _236_ = _154_ & _158_;
  assign _237_ = _150_ & _236_;
  assign _238_ = _166_ & _224_;
  assign _239_ = _165_ & _170_;
  assign _240_ = _163_ & _239_;
  assign _241_ = _237_ & _240_;
  assign _242_ = _235_ & _241_;
  assign _243_ = _182_ & _187_;
  assign _244_ = _178_ & _243_;
  assign _245_ = _196_ & _200_;
  assign _246_ = _192_ & _245_;
  assign _247_ = _244_ & _246_;
  assign _248_ = _212_ & _216_;
  always @(posedge clock)
    _249_ <= _007_;
  always @(posedge clock)
    _250_ <= _028_;
  always @(posedge clock)
    _251_ <= _054_;
  always @(posedge clock)
    _252_ <= _075_;
  assign _112_ = ~a_1;
  assign _012_ = ~_000_;
  assign _007_ = ~_006_;
  assign _028_ = ~_027_;
  assign _054_ = ~_053_;
  assign _068_ = ~_057_;
  assign _075_ = ~_074_;
  assign c_1 = ~_094_;
  assign d_1 = ~_108_;
  assign _131_ = ~b_1;
  assign _118_ = ~_113_;
  assign e_1 = ~_117_;
  assign _121_ = ~_120_;
  assign _126_ = ~_125_;
  assign _129_ = ~_128_;
  assign _146_ = ~_249_;
  assign _134_ = ~_133_;
  assign _137_ = ~_136_;
  assign _140_ = ~_139_;
  assign _143_ = ~_142_;
  assign _166_ = ~_250_;
  assign _148_ = ~_147_;
  assign _150_ = ~_149_;
  assign _152_ = ~_151_;
  assign _154_ = ~_153_;
  assign _156_ = ~_155_;
  assign _158_ = ~_157_;
  assign _161_ = ~_160_;
  assign _163_ = ~_162_;
  assign _165_ = ~_164_;
  assign _185_ = ~_251_;
  assign _168_ = ~_167_;
  assign _170_ = ~_169_;
  assign _172_ = ~_171_;
  assign _176_ = ~_175_;
  assign _178_ = ~_177_;
  assign _180_ = ~_179_;
  assign _182_ = ~_181_;
  assign _184_ = ~_183_;
  assign _203_ = ~_252_;
  assign _187_ = ~_186_;
  assign _190_ = ~_189_;
  assign _192_ = ~_191_;
  assign _194_ = ~_193_;
  assign _196_ = ~_195_;
  assign _198_ = ~_197_;
  assign _200_ = ~_199_;
  assign _206_ = ~_205_;
  assign _208_ = ~_207_;
  assign _210_ = ~_209_;
  assign _212_ = ~_211_;
  assign _214_ = ~_213_;
  assign _216_ = ~_215_;
  assign _219_ = ~_218_;
  assign _221_ = ~_220_;
  assign _223_ = ~_222_;
  assign _226_ = ~_225_;
  assign _228_ = ~_227_;
  assign _230_ = ~_229_;
endmodule

input/syntetic/design/test.v
module test(
clock,a_1_0,a_1_1,a_2_0,a_2_1,c_1_0,c_2_0);
input clock,a_1_0,a_1_1,a_2_0,a_2_1;
output c_1_0,c_2_0;
spec0 spec_sbm0(clock, a_1_0,a_1_1,c_1_0);
spec1 spec_sbm1(clock, a_2_0,a_2_1,c_2_0);
endmodule

input/syntetic/traces/trace.vcd
$version Generated by VerilatedVcd $end
$timescale 1ps $end
 $scope module TOP $end
  $var wire 1 # a_1_0 $end
  $var wire 1 $ a_1_1 $end
  $var wire 1 % a_2_0 $end
  $var wire 1 & a_2_1 $end
  $var wire 1 ' c_1_0 $end
  $var wire 1 ( c_2_0 $end
  $var wire 1 ) clock $end
  $scope module test $end
   $var wire 1 # a_1_0 $end
   $var wire 1 $ a_1_1 $end
   $var wire 1 % a_2_0 $end
   $var wire 1 & a_2_1 $end
   $var wire 1 ' c_1_0 $end
   $var wire 1 ( c_2_0 $end
   $var wire 1 ) clock $end
  $upscope $end
 $upscope $end
$enddefinitions $end


#0
0#
0$
0%
0&
0'
0(
1)
#1
0)
#2
1#
1$
1%
1)
#3
0$
0%
1&
0)
#4
1%
1(
1)
#5
0#
1$
0%
0)
#6
0$
0&
0(
1)
#7
1#
1$
1%
0)
#8
0#
0$
1)
#9
1#
1$
0%
1&
0)
#10
0#
1%
0&
1)
#11
1#
0%
0)
#12
1%
1&
1(
1)
#13
0#
0$
0%
0)
#14
1#
1$
0&
1'
0(
1)
#15
0$
1%
0)
#16
0#
0'
1)
#17
1#
1&
0)
#18
0#
1(
1)
#19
1#
0)
#20
0#
1)
#21
1$
0%
0&
0)
#22
1#
0$
0(
1)
#23
0#
1$
1%
0)
#24
0$
0%
1&
1)
#25
1$
0&
0)
#26
0$
1%
1)
#27
1#
0%
0)
#28
1$
1&
1(
1)
#29
0$
0&
0)
#30
1%
0(
1)
#31
1&
0)
#32
0#
1$
1'
1(
1)
#33
1#
0)
#34
0%
0'
1)
#35
0$
1%
0)
#36
0#
1$
0%
1'
0(
1)
#37
0$
1%
0)
#38
1#
0%
0'
1)
#39
0#
1%
0)
#40
1)
#41
1$
0)
#42
1#
0$
0%
0&
1)
#43
1$
0)
#44
0#
0$
1)
#45
1#
1$
1%
0)
#46
0%
1&
1)
#47
0#
0)
#48
1#
0$
1%
1)
#49
0#
1$
0)
#50
1#
0$
0%
1(
1)
#51
1%
0)
#52
0#
1$
0&
1'
0(
1)
#53
1#
0$
0%
0)
#54
0#
0'
1)
#55
1#
1$
1&
0)
#56
0#
0$
1%
1)
#57
0)
#58
1$
0&
1)
#59
0%
0)
#60
1%
1)
#61
1#
0$
0)
#62
0#
1$
1)
#63
0$
0%
0)
#64
1#
1$
1%
1)
#65
0$
0)
#66
0#
0%
1)
#67
1&
0)
#68
1%
0&
1)
#69
0%
0)
#70
1$
1&
1(
1)
#71
1%
0)
#72
1#
0%
0&
0(
1)
#73
0#
1%
1&
0)
#74
1#
0&
1'
1)
#75
0$
0)
#76
0#
0%
0'
1)
#77
0)
#78
1$
1&
1)
#79
1#
0&
0)
#80
0#
1%
1)
#81
0$
0)
#82
1$
0%
1&
1(
1)
#83
1#
1%
0)
#84
0&
0(
1)
#85
0#
0%
1&
0)
#86
1#
0$
0&
1)
#87
0#
1%
0)
#88
0%
1&
1)
#89
0&
0)
#90
1#
1%
1&
1)
#91
0#
0&
0)
#92
0%
1)
#93
1#
1$
1&
0)
#94
0#
0$
1)
#95
1#
1$
0)
#96
0#
0$
1)
#97
1#
1$
1%
0&
0)
#98
0$
1&
1)
#99
0&
0)
#100
0#
0%
1)
#101
1&
0)
#102
1)
#103
0&
0)
#104
1#
1$
1%
1)
#105
0$
0%
0)
#106
1%
1)
#107
0#
0)
#108
1#
1$
1'
1)
#109
0%
1&
0)
#110
0#
0$
0'
1(
1)
#111
1#
1$
1%
0&
0)
#112
0#
0$
0(
1)
#113
0)
#114
0%
1)
#115
1$
1%
1&
0)
#116
1#
0$
0&
1)
#117
0#
1$
0%
1&
0)
#118
1#
1'
1(
1)
#119
1%
0&
0)
#120
0#
0%
1&
0(
1)
#121
1#
1%
0)
#122
0$
0&
0'
1)
#123
1$
0%
1&
0)
#124
0#
1'
1(
1)
#125
1#
0$
0&
0)
#126
1&
0'
0(
1)
#127
1%
0&
0)
#128
1$
1&
1'
1)
#129
0#
0$
0)
#130
1#
0%
0&
0'
1)
#131
0#
1&
0)
#132
1#
0&
1)
#133
0#
0)
#134
1%
1)
#135
1$
0%
0)
#136
1#
1%
1)
#137
0$
0%
1&
0)
#138
0#
1(
1)
#139
1%
0)
#140
1#
1$
0&
0(
1)
#141
0#
0%
1&
0)
#142
0$
0&
1)
#143
1&
0)
#144
1#
1$
1%
1)
#145
0&
0)
#146
1'
1)
#147
0%
1&
0)
#148
1%
0&
1)
#149
0#
0$
0%
1&
0)
#150
1#
1%
0&
0'
1)
#151
1$
0%
1&
0)
#152
0#
1%
1'
1(
1)
#153
1#
0$
0%
0)
#154
1$
0'
1)
#155
0#
0$
1%
0&
0)
#156
1#
1$
1&
1'
0(
1)
#157
0#
0)
#158
1#
0%
1(
1)
#159
0#
0$
1%
0&
0)
#160
1#
0%
0'
0(
1)
#161
1&
0)
#162
0#
1%
0&
1)
#163
0)
#164
1#
0%
1&
1(
1)
#165
0#
1$
1%
0)
#166
1#
0&
1'
0(
1)
#167
0$
0%
0)
#168
0#
1$
1%
1&
1(
1)
#169
0%
0)
#170
1#
0'
1)
#171
0&
0)
#172
0$
0(
1)
#173
1$
0)
#174
0#
0$
1%
1&
1)
#175
1#
0&
0)
#176
1&
1(
1)
#177
0#
0%
0)
#178
1%
1)
#179
1#
1$
0)
#180
0&
0(
1)
#181
0#
0%
0)
#182
1#
0$
1&
1(
1)
#183
0#
1$
1%
0&
0)
#184
1#
1&
1'
0(
1)
#185
0#
0%
0)
#186
1(
1)
#187
1#
0)
#188
1%
0&
0'
0(
1)
#189
0#
0%
1&
0)
#190
0$
1(
1)
#191
1#
0&
0)
#192
1&
0(
1)
#193
0#
0)
#194
1#
0&
1)
#195
1&
0)
#196
1$
0&
1'
1)
#197
0$
1%
0)
#198
0#
0'
1)
#199
0%
0)
#200
1#
1%
1)
#201
1$
0%
0)
#202
0#
0$
1%
1)
#203
1#
1$
1&
0)
#204
0%
0&
1)
#205
1%
1&
0)
#206
0$
0%
1)
#207
0&
0)
#208
0#
1$
1'
1)
#209
0$
1%
1&
0)
#210
1#
0%
0'
1)
#211
0#
1$
1%
0&
0)
#212
1'
1)
#213
1#
0$
0)
#214
0#
1$
1&
0'
1(
1)
#215
1#
0$
0%
0)
#216
1%
1)
#217
0#
0&
0)
#218
1#
1&
1)
#219
0)
#220
0#
1$
1'
1)
#221
0$
0%
0)
#222
1$
0'
1)
#223
0$
1%
0)
#224
1#
1$
0&
0(
1)
#225
0#
0%
1&
0)
#226
1%
1'
1(
1)
#227
0%
0&
0)
#228
1#
0$
1%
0'
0(
1)
#229
1$
0%
0)
#230
0#
0$
1&
1(
1)
#231
1%
0&
0)
#232
1$
0%
1&
0(
1)
#233
0$
1%
0&
0)
#234
1#
1)
#235
0#
1&
0)
#236
1#
1$
0&
1'
1)
#237
0#
0%
0)
#238
1#
1&
1(
1)
#239
1%
0)
#240
0#
0%
0&
0(
1)
#241
1%
0)
#242
0%
0'
1)
#243
1#
1%
1&
0)
#244
0$
0&
1)
#245
0%
1&
0)
#246
0#
1%
1(
1)
#247
0%
0&
0)
#248
1%
1&
1)
#249
1#
0&
0)
#250
0#
1$
1&
1)
#251
0$
0)
#252
1#
1$
0%
0&
0(
1)
#253
1%
1&
0)
#254
0#
0$
0%
1)
#255
1#
0&
0)
#256
0#
1$
1%
1)
#257
0%
1&
0)
#258
1#
0$
1%
0&
1)
#259
1$
0)
#260
0%
1'
1)
#261
0$
1%
0)
#262
0#
1$
1)
#263
1#
1&
0)
#264
0$
0%
0&
0'
1)
#265
0#
1%
1&
0)
#266
0&
1)
#267
1#
0%
1&
0)
#268
0&
1)
#269
0#
1$
0)
#270
1#
0$
1)
#271
1$
1%
1&
0)
#272
0#
0%
1'
1)
#273
1#
1%
0)
#274
0#
0$
0'
1)
#275
1#
1$
0%
0)
#276
1%
1(
1)
#277
0#
0$
0&
0)
#278
1#
1$
0%
1'
0(
1)
#279
1%
0)
#280
0%
1)
#281
0#
0)
#282
1%
1)
#283
1#
0%
0)
#284
1%
0'
1)
#285
0$
0%
1&
0)
#286
1%
1(
1)
#287
0&
0)
#288
0#
1$
0%
1'
0(
1)
#289
0$
1&
0)
#290
1#
1$
0'
1)
#291
0$
1%
0)
#292
0%
1)
#293
0)
#294
0#
1$
1'
1)
#295
1#
1%
0&
0)
#296
0#
0$
0%
0'
1)
#297
1#
1$
0)
#298
0#
0$
1%
1)
#299
1#
0)
#300
0#
1$
1&
1(
1)
#301
0%
0&
0)
#302
1#
0$
1&
1)
#303
1$
1%
0)
#304
0#
1'
0(
1)
#305
0$
0%
0&
0)
#306
1#
1$
0'
1)
#307
1%
0)
#308
0$
1&
1)
#309
1$
0%
0)
#310
0#
0$
1%
0&
1)
#311
1#
1&
0)
#312
1$
0&
1)
#313
0#
1&
0)
#314
1#
0$
0%
0&
1)
#315
0#
1$
1%
1&
0)
#316
0$
1)
#317
1#
1$
0&
0)
#318
0#
1&
1(
1)
#319
1#
0%
0)
#320
0&
0(
1)
#321
0)
#322
0#
1%
1&
1'
1)
#323
1#
0$
0&
0)
#324
0#
1$
1&
0'
1(
1)
#325
1#
0$
0&
0)
#326
0#
1&
1)
#327
1#
1$
0%
0)
#328
0$
0&
0(
1)
#329
0#
1$
0)
#330
1#
1'
1)
#331
0#
0$
0)
#332
1#
1$
1&
1)
#333
1%
0&
0)
#334
0$
0%
1&
0'
1)
#335
1$
0)
#336
1%
1'
1)
#337
0$
0&
0)
#338
0#
1$
0%
1&
1(
1)
#339
1#
0)
#340
0#
0$
0&
0'
0(
1)
#341
1$
1&
0)
#342
1#
0$
0&
1)
#343
1%
1&
0)
#344
0%
1)
#345
1$
1%
0&
0)
#346
0#
0$
1&
1)
#347
0)
#348
1#
1$
0%
0&
1)
#349
0#
0$
1%
0)
#350
1$
0%
1'
1)
#351
1%
1&
0)
#352
1#
0%
0'
1)
#353
0#
0$
0)
#354
1$
0&
1'
1)
#355
1#
1&
0)
#356
0#
0$
0&
0'
1)
#357
1#
1$
1%
0)
#358
1)
#359
0$
0%
0)
#360
0#
1$
1&
1'
1(
1)
#361
0$
0)
#362
1#
1$
0'
0(
1)
#363
0$
1%
0&
0)
#364
1$
0%
1&
1'
1)
#365
0&
0)
#366
0#
1%
1&
1)
#367
1#
0$
0)
#368
1$
0'
1(
1)
#369
0#
0$
0)
#370
1#
1$
0%
1'
1)
#371
0)
#372
0#
0$
0&
0'
0(
1)
#373
0)
#374
1#
1$
1)
#375
0$
1&
0)
#376
0#
1)
#377
1#
1$
0&
0)
#378
0$
1)
#379
0#
1$
1&
0)
#380
1#
0$
1%
1)
#381
1$
0%
0)
#382
0&
1'
1)
#383
0#
1&
0)
#384
1%
1)
#385
1#
0%
0&
0)
#386
0$
1%
1&
0'
1(
1)
#387
0#
1$
0)
#388
1#
0$
0%
0&
0(
1)
#389
1$
1&
0)
#390
0#
0$
0&
1)
#391
1#
1%
1&
0)
#392
0#
1$
1)
#393
0&
0)
#394
0$
0%
1)
#395
1#
1&
0)
#396
1$
0&
1)
#397
0#
0$
0)
#398
1%
1&
1)
#399
0&
0)
#400
0%
1&
1(
1)
#401
1$
0&
0)
#402
0$
1%
1&
0(
1)
#403
0%
0&
0)
#404
1#
1%
1&
1(
1)
#405
1$
0)
#406
0#
0$
0%
1)
#407
1#
1$
1%
0&
0)
#408
0#
0%
0(
1)
#409
0$
0)
#410
1#
1$
1)
#411
0$
1&
0)
#412
0#
1$
1%
0&
1'
1)
#413
1#
0$
0)
#414
0%
0'
1)
#415
1%
1&
0)
#416
1$
1'
1)
#417
0#
0)
#418
1#
0%
1(
1)
#419
0#
0$
1%
0)
#420
0'
0(
1)
#421
1#
1$
0%
0)
#422
1(
1)
#423
0#
0)
#424
0&
1'
0(
1)
#425
1#
0$
1%
1&
0)
#426
0#
1$
0%
0'
1)
#427
1#
1%
0&
0)
#428
0$
1)
#429
1$
0%
1&
0)
#430
0#
1%
0&
1'
1)
#431
1#
0%
0)
#432
0$
0'
1)
#433
1$
1%
0)
#434
0#
0$
1&
1)
#435
1#
0%
0)
#436
1$
0&
1)
#437
0#
1&
0)
#438
1#
1%
0&
1'
1)
#439
0#
0)
#440
1#
0$
0%
1&
0'
1(
1)
#441
0#
0)
#442
1$
1%
0&
1'
0(
1)
#443
1#
0$
1&
0)
#444
1$
0'
1(
1)
#445
0#
0$
0%
0&
0)
#446
1$
1%
1&
1'
1)
#447
0$
0&
0)
#448
1#
1$
0'
0(
1)
#449
0#
0%
1&
0)
#450
1#
0$
1%
0&
1)
#451
0)
#452
0%
1&
1(
1)
#453
0#
0&
0)
#454
1$
1&
1'
0(
1)
#455
1#
0&
0)
#456
0#
0$
0'
1)
#457
1$
1%
1&
0)
#458
0$
1)
#459
1#
0%
0&
0)
#460
0#
1&
1(
1)
#461
1#
1%
0&
0)
#462
1$
0%
0(
1)
#463
0#
0)
#464
1#
1%
1&
1'
1)
#465
0#
0$
0%
0&
0)
#466
1#
1&
0'
1(
1)
#467
1%
0&
0)
#468
1$
1&
1'
0(
1)
#469
0$
0&
0)
#470
0#
1$
0%
1)
#471
0$
1%
0)
#472
1#
0%
1&
0'
1)
#473
0)
#474
0#
1%
0&
1)
#475
1#
1$
0%
1&
0)
#476
0#
1%
0&
1)
#477
0$
0%
0)
#478
1)
#479
1&
0)
#480
0&
1)
#481
1#
1%
0)
#482
1$
0%
1&
1)
#483
0#
0$
0&
0)
#484
1$
1%
1'
1)
#485
0%
0)
#486
0$
0'
1)
#487
1#
1%
0)
#488
1$
0%
1)
#489
0$
0)
#490
1%
1&
1)
#491
1$
0&
0)
#492
0#
0$
0%
1)
#493
0)
#494
1$
1%
1&
1)
#495
1#
0$
0%
0)
#496
0#
1$
1%
0&
1)
#497
1&
0)
