input/syntetic/design/spec2.v
/* Generated by Yosys 0.47+149 (git sha1 889894a6d, clang++ 18.1.8 -fPIC -O3) */

module spec2(clock, a_3_0, a_3_1, c_3_0);
  wire _00_;
  wire _01_;
  wire _02_;
  wire _03_;
  wire _04_;
  wire _05_;
  wire _06_;
  wire _07_;
  wire _08_;
  wire _09_;
  wire _10_;
  wire _11_;
  wire _12_;
  wire _13_;
  wire _14_;
  wire _15_;
  wire _16_;
  wire _17_;
  wire _18_;
  wire _19_;
  wire _20_;
  wire _21_;
  wire _22_;
  wire _23_;
  wire _24_;
  wire _25_;
  wire _26_;
  wire _27_;
  wire _28_;
  wire _29_;
  wire _30_;
  wire _31_;
  wire _32_;
  wire _33_;
  wire _34_;
  wire _35_;
  wire _36_;
  reg _37_ = 1'h0;
  input a_3_0;
  wire a_3_0;
  input a_3_1;
  wire a_3_1;
  output c_3_0;
  reg c_3_0 = 1'h0;
  input clock;
  wire clock;
  assign _00_ = _35_ & _36_;
  assign _02_ = a_3_0 & a_3_1;
  assign _03_ = _02_ & _36_;
  assign _05_ = _13_ & a_3_1;
  assign _06_ = _05_ & _36_;
  assign _08_ = _30_ & c_3_0;
  assign _09_ = _02_ & _08_;
  assign _11_ = _05_ & _08_;
  assign _14_ = _35_ & _08_;
  assign _16_ = _37_ & c_3_0;
  assign _17_ = a_3_0 & _16_;
  assign _19_ = _01_ & _07_;
  assign _20_ = _34_ & _19_;
  assign _21_ = _15_ & _18_;
  assign _22_ = _12_ & _21_;
  assign _23_ = _20_ & _22_;
  assign _26_ = _04_ & _07_;
  assign _27_ = _10_ & _12_;
  assign _28_ = _26_ & _27_;
  assign _32_ = _30_ & _31_;
  assign _33_ = a_3_0 & _32_;
  assign _35_ = a_3_0 & _25_;
  assign _36_ = _37_ & _31_;
  always @(posedge clock)
    _37_ <= _24_;
  always @(posedge clock)
    c_3_0 <= _29_;
  assign _13_ = ~a_3_0;
  assign _01_ = ~_00_;
  assign _04_ = ~_03_;
  assign _07_ = ~_06_;
  assign _10_ = ~_09_;
  assign _12_ = ~_11_;
  assign _25_ = ~a_3_1;
  assign _15_ = ~_14_;
  assign _18_ = ~_17_;
  assign _24_ = ~_23_;
  assign _30_ = ~_37_;
  assign _29_ = ~_28_;
  assign _31_ = ~c_3_0;
  assign _34_ = ~_33_;
endmodule

input/syntetic/design/spec1.v
/* Generated by Yosys 0.47+149 (git sha1 889894a6d, clang++ 18.1.8 -fPIC -O3) */

module spec1(clock, a_2_0, a_2_1, c_2_0);
  wire _00_;
  wire _01_;
  wire _02_;
  wire _03_;
  wire _04_;
  wire _05_;
  wire _06_;
  wire _07_;
  wire _08_;
  wire _09_;
  wire _10_;
  wire _11_;
  wire _12_;
  wire _13_;
  wire _14_;
  wire _15_;
  wire _16_;
  wire _17_;
  wire _18_;
  wire _19_;
  wire _20_;
  wire _21_;
  wire _22_;
  wire _23_;
  wire _24_;
  wire _25_;
  wire _26_;
  wire _27_;
  wire _28_;
  wire _29_;
  wire _30_;
  wire _31_;
  wire _32_;
  wire _33_;
  wire _34_;
  wire _35_;
  wire _36_;
  reg _37_ = 1'h0;
  input a_2_0;
  wire a_2_0;
  input a_2_1;
  wire a_2_1;
  output c_2_0;
  reg c_2_0 = 1'h0;
  input clock;
  wire clock;
  assign _00_ = _35_ & _36_;
  assign _02_ = a_2_0 & a_2_1;
  assign _03_ = _02_ & _36_;
  assign _05_ = _13_ & a_2_1;
  assign _06_ = _05_ & _36_;
  assign _08_ = _30_ & c_2_0;
  assign _09_ = _02_ & _08_;
  assign _11_ = _05_ & _08_;
  assign _14_ = _35_ & _08_;
  assign _16_ = _37_ & c_2_0;
  assign _17_ = a_2_0 & _16_;
  assign _19_ = _01_ & _07_;
  assign _20_ = _34_ & _19_;
  assign _21_ = _15_ & _18_;
  assign _22_ = _12_ & _21_;
  assign _23_ = _20_ & _22_;
  assign _26_ = _04_ & _07_;
  assign _27_ = _10_ & _12_;
  assign _28_ = _26_ & _27_;
  assign _32_ = _30_ & _31_;
  assign _33_ = a_2_0 & _32_;
  assign _35_ = a_2_0 & _25_;
  assign _36_ = _37_ & _31_;
  always @(posedge clock)
    _37_ <= _24_;
  always @(posedge clock)
    c_2_0 <= _29_;
  assign _13_ = ~a_2_0;
  assign _01_ = ~_00_;
  assign _04_ = ~_03_;
  assign _07_ = ~_06_;
  assign _10_ = ~_09_;
  assign _12_ = ~_11_;
  assign _25_ = ~a_2_1;
  assign _15_ = ~_14_;
  assign _18_ = ~_17_;
  assign _24_ = ~_23_;
  assign _30_ = ~_37_;
  assign _29_ = ~_28_;
  assign _31_ = ~c_2_0;
  assign _34_ = ~_33_;
endmodule

input/syntetic/design/spec0.v
/* Generated by Yosys 0.47+149 (git sha1 889894a6d, clang++ 18.1.8 -fPIC -O3) */

module spec0(clock, a_1_0, a_1_1, c_1_0);
  wire _00_;
  wire _01_;
  wire _02_;
  wire _03_;
  wire _04_;
  wire _05_;
  wire _06_;
  wire _07_;
  wire _08_;
  wire _09_;
  wire _10_;
  wire _11_;
  wire _12_;
  wire _13_;
  wire _14_;
  wire _15_;
  wire _16_;
  wire _17_;
  wire _18_;
  wire _19_;
  wire _20_;
  wire _21_;
  wire _22_;
  wire _23_;
  wire _24_;
  wire _25_;
  wire _26_;
  wire _27_;
  wire _28_;
  wire _29_;
  wire _30_;
  wire _31_;
  wire _32_;
  wire _33_;
  wire _34_;
  wire _35_;
  wire _36_;
  reg _37_ = 1'h0;
  input a_1_0;
  wire a_1_0;
  input a_1_1;
  wire a_1_1;
  output c_1_0;
  reg c_1_0 = 1'h0;
  input clock;
  wire clock;
  assign _00_ = _35_ & _36_;
  assign _02_ = a_1_0 & a_1_1;
  assign _03_ = _02_ & _36_;
  assign _05_ = _13_ & a_1_1;
  assign _06_ = _05_ & _36_;
  assign _08_ = _30_ & c_1_0;
  assign _09_ = _02_ & _08_;
  assign _11_ = _05_ & _08_;
  assign _14_ = _35_ & _08_;
  assign _16_ = _37_ & c_1_0;
  assign _17_ = a_1_0 & _16_;
  assign _19_ = _01_ & _07_;
  assign _20_ = _34_ & _19_;
  assign _21_ = _15_ & _18_;
  assign _22_ = _12_ & _21_;
  assign _23_ = _20_ & _22_;
  assign _26_ = _04_ & _07_;
  assign _27_ = _10_ & _12_;
  assign _28_ = _26_ & _27_;
  assign _32_ = _30_ & _31_;
  assign _33_ = a_1_0 & _32_;
  assign _35_ = a_1_0 & _25_;
  assign _36_ = _37_ & _31_;
  always @(posedge clock)
    _37_ <= _24_;
  always @(posedge clock)
    c_1_0 <= _29_;
  assign _13_ = ~a_1_0;
  assign _01_ = ~_00_;
  assign _04_ = ~_03_;
  assign _07_ = ~_06_;
  assign _10_ = ~_09_;
  assign _12_ = ~_11_;
  assign _25_ = ~a_1_1;
  assign _15_ = ~_14_;
  assign _18_ = ~_17_;
  assign _24_ = ~_23_;
  assign _30_ = ~_37_;
  assign _29_ = ~_28_;
  assign _31_ = ~c_1_0;
  assign _34_ = ~_33_;
endmodule

input/syntetic/design/test.v
module test(
clock,a_1_0,a_1_1,a_2_0,a_2_1,a_3_0,a_3_1,c_1_0,c_2_0,c_3_0);
input clock,a_1_0,a_1_1,a_2_0,a_2_1,a_3_0,a_3_1;
output c_1_0,c_2_0,c_3_0;
spec0 spec_sbm0(clock, a_1_0,a_1_1,c_1_0);
spec1 spec_sbm1(clock, a_2_0,a_2_1,c_2_0);
spec2 spec_sbm2(clock, a_3_0,a_3_1,c_3_0);
endmodule

input/syntetic/traces/trace.vcd
$version Generated by VerilatedVcd $end
$timescale 1ps $end
 $scope module TOP $end
  $var wire 1 # clock $end
  $var wire 1 $ a_1_0 $end
  $var wire 1 % a_1_1 $end
  $var wire 1 & a_2_0 $end
  $var wire 1 ' a_2_1 $end
  $var wire 1 ( a_3_0 $end
  $var wire 1 ) a_3_1 $end
  $var wire 1 * c_1_0 $end
  $var wire 1 + c_2_0 $end
  $var wire 1 , c_3_0 $end
  $scope module test $end
   $var wire 1 # clock $end
   $var wire 1 $ a_1_0 $end
   $var wire 1 % a_1_1 $end
   $var wire 1 & a_2_0 $end
   $var wire 1 ' a_2_1 $end
   $var wire 1 ( a_3_0 $end
   $var wire 1 ) a_3_1 $end
   $var wire 1 * c_1_0 $end
   $var wire 1 + c_2_0 $end
   $var wire 1 , c_3_0 $end
   $scope module spec_sbm0 $end
    $var wire 1 $ a_1_0 $end
    $var wire 1 % a_1_1 $end
    $var wire 1 * c_1_0 $end
    $var wire 1 # clock $end
   $upscope $end
   $scope module spec_sbm1 $end
    $var wire 1 & a_2_0 $end
    $var wire 1 ' a_2_1 $end
    $var wire 1 + c_2_0 $end
    $var wire 1 # clock $end
   $upscope $end
   $scope module spec_sbm2 $end
    $var wire 1 ( a_3_0 $end
    $var wire 1 ) a_3_1 $end
    $var wire 1 , c_3_0 $end
    $var wire 1 # clock $end
   $upscope $end
  $upscope $end
 $upscope $end
$enddefinitions $end


#0
1#
0$
0%
0&
0'
0(
0)
0*
0+
0,
#1
0#
#2
1#
1$
1&
1'
1(
1)
#3
0#
0'
0)
#4
1#
0$
1%
0(
1*
#5
0#
1$
0%
1)
#6
1#
0&
1(
0*
#7
0#
1'
0(
#8
1#
1&
1,
#9
0#
0$
1%
0&
1(
0)
#10
1#
0%
1&
0(
1)
1+
0,
#11
0#
1$
1%
0&
0'
0)
#12
1#
1'
1(
#13
0#
1&
0'
#14
1#
0$
0&
1*
0+
#15
0#
0%
1&
1'
0(
#16
1#
1$
0'
1(
0*
#17
0#
0$
0&
0(
1)
#18
1#
1(
1,
#19
0#
1&
#20
1#
0&
1'
0(
#21
0#
1$
1%
1&
0'
1(
0)
#22
1#
1)
0,
#23
0#
0$
1'
#24
1#
1$
0&
0)
1*
1+
#25
0#
0%
#26
1#
1%
0(
0+
#27
0#
0'
1(
#28
1#
0$
1&
1)
#29
0#
0%
0(
#30
1#
0&
0*
1,
#31
0#
1%
1&
1'
1(
#32
1#
1$
0'
0(
0,
#33
0#
0&
1(
#34
1#
1'
0(
1*
1+
#35
0#
0'
#36
1#
0$
0%
1'
0)
0*
0+
#37
0#
1&
0'
1(
1)
#38
1#
1$
1%
0&
0)
#39
0#
0(
1)
#40
1#
0$
0%
1&
0)
#41
0#
1$
1%
1'
#42
1#
0$
0%
0'
1(
#43
0#
1$
0(
1)
#44
1#
0$
0&
1'
1(
0)
1+
#45
0#
0'
#46
1#
0+
#47
0#
1)
#48
1#
1%
1&
1,
#49
0#
1$
0%
0&
1'
#50
1#
0$
1&
1+
#51
0#
1%
0&
0'
0(
0)
#52
1#
1$
0%
0+
0,
#53
0#
0$
1&
1'
1)
#54
1#
0'
1(
0)
#55
0#
1%
0&
1)
#56
1#
1&
1'
1+
1,
#57
0#
0&
#58
1#
0%
0(
0)
0,
#59
0#
1%
0'
1(
#60
1#
1$
0%
0(
1)
0+
#61
0#
1%
0)
#62
1#
0%
1)
#63
0#
0$
1'
1(
0)
#64
1#
1$
1%
1&
0(
1*
#65
0#
0%
0'
1)
#66
1#
0$
1%
0&
1'
1(
1+
#67
0#
0'
0(
0)
#68
1#
1$
0*
0+
#69
0#
0$
0%
#70
1#
1&
1'
1(
1)
#71
0#
1$
0'
0(
0)
#72
1#
0$
0&
1(
1)
1,
#73
0#
1%
1&
1'
#74
1#
0&
0'
0(
#75
0#
1$
1'
0)
#76
1#
0$
0%
0'
1(
0,
#77
0#
1$
1)
#78
1#
1'
0)
#79
0#
0$
1&
1)
#80
1#
1$
0)
#81
0#
1)
#82
1#
0&
1+
1,
#83
0#
0$
#84
1#
1$
0(
0+
#85
0#
1&
0'
0)
#86
1#
1%
1'
1(
1*
0,
#87
0#
0$
0'
0(
#88
1#
0&
1)
1,
#89
0#
0%
0)
#90
1#
1(
0*
0,
#91
0#
1$
1&
1'
0(
1)
#92
1#
1%
0&
0)
#93
0#
0%
0'
1(
#94
1#
1&
1'
#95
0#
0$
0&
0(
#96
1#
1$
1%
0'
1)
1*
1,
#97
0#
1&
1'
#98
1#
0%
1(
0*
0,
#99
0#
0(
#100
1#
0$
1%
0&
0'
1*
1,
#101
0#
1&
1(
#102
1#
1$
0*
0,
#103
0#
0$
0%
#104
1#
1$
0&
1,
#105
0#
1%
1'
#106
1#
0$
1&
0(
0)
1*
0,
#107
0#
0'
#108
1#
0&
1'
0*
1+
#109
0#
1$
0'
#110
1#
1'
0+
#111
0#
1&
1)
#112
1#
0%
0&
0)
#113
0#
0$
1%
1(
1)
#114
1#
1&
0(
1*
#115
0#
0%
0)
#116
1#
1$
0*
1+
#117
0#
1%
0'
#118
1#
0&
1'
1(
1*
#119
0#
0%
0'
#120
1#
0$
1%
1&
1'
1)
0+
1,
#121
0#
0&
0(
#122
1#
0)
0*
1+
0,
#123
0#
1$
1&
1(
1)
#124
1#
0'
0(
0)
0+
#125
0#
0$
0%
1'
1(
1)
#126
1#
1$
0)
1+
#127
0#
0$
0&
#128
1#
1$
0(
1)
1,
#129
0#
0$
0'
1(
0)
#130
1#
1$
1'
0(
1)
0+
0,
#131
0#
0$
1&
0'
#132
1#
0&
1'
1(
0)
#133
0#
1%
0'
0(
#134
1#
0%
1'
1(
1)
1,
#135
0#
1$
0(
0)
#136
1#
0$
1%
1&
1(
1)
#137
0#
1$
0%
#138
1#
0$
1%
0&
0(
1+
#139
0#
0%
0'
#140
1#
1$
1%
1(
0+
0,
#141
0#
0%
0(
#142
1#
0$
1&
1(
1,
#143
0#
1$
1%
0&
#144
1#
1'
0(
1+
#145
0#
0'
0)
#146
1#
1'
1(
1)
1*
0+
0,
#147
0#
0'
#148
1#
0(
0)
#149
0#
0%
1'
1(
#150
1#
1&
0*
#151
0#
0&
1)
#152
1#
0$
1&
0'
0(
1,
#153
0#
1%
#154
1#
0&
0)
0,
#155
0#
1(
1)
#156
1#
0%
#157
0#
1$
1%
0)
#158
1#
0$
0%
1&
1'
#159
0#
1)
#160
1#
1%
0)
1+
#161
0#
1$
0%
0&
0(
1)
#162
1#
1&
0'
0+
1,
#163
0#
1%
1'
0)
#164
1#
0&
1*
1+
0,
#165
0#
0$
0'
#166
1#
1(
1)
0+
#167
0#
1$
#168
1#
0$
0*
1,
#169
0#
1$
0%
1&
1'
#170
1#
0$
1%
0&
0'
0(
#171
0#
1$
0%
#172
1#
0$
1%
1&
0,
#173
0#
1$
#174
1#
0$
0%
1'
1+
#175
0#
1$
1%
0&
0'
#176
1#
0$
1&
1'
1(
#177
0#
1$
0%
0&
0'
0)
#178
1#
1)
0+
1,
#179
0#
0$
1&
0(
0)
#180
1#
1)
#181
0#
1$
1(
#182
1#
1%
0(
0,
#183
0#
0&
1'
1(
0)
#184
1#
1&
0(
1)
1*
1+
#185
0#
0&
0)
#186
1#
0$
0%
1&
1)
0*
#187
0#
1%
#188
1#
0%
0'
0)
0+
#189
0#
1%
1'
1)
#190
1#
1$
0%
1(
1+
#191
0#
0'
0)
#192
1#
0$
0&
1'
#193
0#
#194
1#
1$
1%
1&
0(
1)
0+
1,
#195
0#
0$
0'
1(
0)
#196
1#
1$
0&
1'
0(
1*
1+
0,
#197
0#
0%
1&
1)
#198
1#
0$
0&
0'
0*
0+
#199
0#
1$
1'
0)
#200
1#
1(
#201
0#
0$
1%
0(
1)
#202
1#
1$
1*
1,
#203
0#
1(
#204
1#
0$
0%
0'
0(
0*
0,
#205
0#
1$
1&
1'
#206
1#
1%
0&
1(
#207
0#
0%
0(
0)
#208
1#
0$
1%
1(
1)
1*
1,
#209
0#
1$
#210
1#
0%
0(
0)
0*
0,
#211
0#
1%
1(
#212
1#
0%
1&
#213
0#
0$
1%
1)
#214
1#
0%
0(
1+
1,
#215
0#
1$
0&
1(
#216
1#
0)
0,
#217
0#
1%
1&
0(
#218
1#
0&
0'
1(
1)
1*
0+
1,
#219
0#
0$
0%
1&
1'
0(
0)
#220
1#
0'
1)
0*
#221
0#
0&
1'
0)
#222
1#
1%
1&
1)
1+
0,
#223
0#
1(
0)
#224
1#
1$
0(
1)
#225
0#
0)
#226
1#
0'
1)
1*
0+
#227
0#
0$
0%
0&
1'
0)
#228
1#
1%
1&
0'
1)
#229
0#
1$
0%
1(
0)
#230
1#
0$
1%
0&
1'
0(
1)
0*
1+
#231
0#
1$
1(
0)
#232
1#
0$
0'
1)
0+
#233
0#
1$
0%
1'
0(
0)
#234
1#
1&
0'
#235
0#
0$
1%
1'
1(
1)
#236
1#
0&
0'
0(
0)
1*
#237
0#
0%
1&
1'
1(
1)
#238
1#
0&
0'
0(
0*
#239
0#
1$
1%
1&
1'
#240
1#
0%
0&
0)
#241
0#
0$
1(
#242
1#
1%
1&
0(
1)
1*
#243
0#
0'
1(
#244
1#
1$
0%
1'
0(
0)
0*
1+
#245
0#
1%
1(
#246
1#
1*
#247
0#
0$
0'
1)
#248
1#
1'
0(
0)
#249
0#
0%
0&
0'
#250
1#
1$
1&
1'
1)
0*
#251
0#
0$
0&
0'
1(
0)
#252
1#
1&
1'
0(
1)
#253
0#
0&
0'
1(
#254
1#
1$
1%
1'
#255
0#
0$
0%
1&
0(
#256
1#
1$
1%
0'
0)
1*
0+
#257
0#
0$
1'
1)
#258
1#
1$
0&
1(
0)
1+
#259
0#
0$
1&
0(
#260
1#
0+
#261
0#
1$
0%
0'
1(
#262
1#
0$
1%
0*
#263
0#
0&
1'
0(
#264
1#
1)
1+
1,
#265
0#
0%
0)
#266
1#
1%
0'
1(
0+
0,
#267
0#
#268
1#
1$
0%
1&
0(
#269
0#
0$
1%
0&
#270
1#
1$
1'
1(
1)
1*
1+
#271
0#
0$
0)
#272
1#
0%
1&
0*
0+
#273
0#
0&
0(
#274
1#
1$
1&
1)
1+
1,
#275
0#
0&
0'
#276
1#
0$
1'
1(
0,
#277
0#
1$
1&
0'
0)
#278
1#
1%
1'
0+
#279
0#
0$
1)
#280
1#
1$
0&
0'
0)
1*
#281
0#
0$
1&
1)
#282
1#
1$
1'
0(
0)
#283
0#
0$
0%
0&
1)
#284
1#
1$
1%
1(
0)
1+
#285
0#
0%
1&
0(
1)
#286
1#
0&
1(
0*
0+
1,
#287
0#
0(
#288
1#
0$
1&
#289
0#
1$
0'
#290
1#
1%
0&
1(
0,
#291
0#
0$
0%
1&
0(
#292
1#
1%
1*
1,
#293
0#
1$
0&
1'
#294
1#
0)
0*
1+
0,
#295
0#
0%
0'
1)
#296
1#
1%
1'
1(
1*
0+
#297
0#
0$
0(
0)
#298
1#
1&
0'
1(
#299
0#
1$
0(
1)
#300
1#
0$
0*
1,
#301
0#
1$
0)
#302
1#
0$
0&
1'
1+
0,
#303
0#
0%
0'
1(
1)
#304
1#
1&
1'
0(
0)
0+
#305
0#
1$
0&
0'
1(
1)
#306
1#
0$
1%
#307
0#
0%
0)
#308
1#
1'
1)
1,
#309
0#
0(
#310
1#
1%
1&
1(
0)
0,
#311
0#
0%
0'
#312
1#
1$
0&
1'
1)
1+
1,
#313
0#
1%
1&
0(
0)
#314
1#
0$
0%
0'
0+
0,
#315
0#
1%
1(
#316
1#
0&
1'
0(
1+
#317
0#
1&
0'
1(
1)
#318
1#
0%
0)
0+
#319
0#
0&
0(
#320
1#
1%
#321
0#
1$
0%
1&
#322
1#
0$
1%
1'
#323
0#
1$
0%
0&
0'
1)
#324
1#
0$
1&
0)
#325
0#
1$
#326
1#
0$
1'
1)
1+
#327
0#
1$
0'
1(
0)
#328
1#
0$
1'
#329
0#
0&
0'
0(
#330
1#
1$
1%
1&
1(
1)
0+
1,
#331
0#
0%
0&
0(
#332
1#
1%
1&
1(
0)
1*
0,
#333
0#
0$
#334
1#
1$
0&
1'
0(
1)
1+
1,
#335
0#
0'
1(
0)
#336
1#
0%
1'
0*
0+
0,
#337
0#
0$
0'
1)
#338
1#
1$
1%
1&
0)
1*
#339
0#
0%
0&
1'
0(
#340
1#
0$
1(
0*
1+
#341
0#
1$
1%
1&
0'
0(
#342
1#
0%
0&
1'
1(
1)
0+
1,
#343
0#
1%
1&
0(
0)
#344
1#
0%
0'
0,
#345
0#
0$
1%
0&
#346
1#
1$
0%
1&
1'
1)
1+
#347
0#
0$
1(
0)
#348
1#
1$
1%
0(
1*
#349
0#
0%
1(
#350
1#
0$
0&
0'
0(
1)
0*
0+
#351
0#
1&
1(
0)
#352
1#
1%
0&
1)
#353
0#
0%
1'
0(
0)
#354
1#
1%
0'
1(
#355
0#
1&
1'
1)
#356
1#
0%
0&
0'
1,
#357
0#
1&
1'
#358
1#
1%
0&
0'
0(
#359
0#
#360
1#
1$
0%
1&
1(
0,
#361
0#
0$
1%
1'
0)
#362
1#
0&
1)
1*
1+
1,
#363
0#
1&
0(
#364
1#
1$
0&
0'
0*
0+
#365
0#
0$
1&
1'
#366
1#
0%
0&
0)
0,
#367
0#
1$
1%
1(
#368
1#
0%
0(
#369
0#
1(
1)
#370
1#
0'
0)
#371
0#
0$
1'
#372
1#
1%
1&
0'
0(
1)
1*
1,
#373
0#
0%
0&
1'
1(
#374
1#
1$
0'
0(
0*
0,
#375
0#
0$
1%
1&
1'
1(
0)
#376
1#
0&
1)
1*
#377
0#
1$
0(
#378
1#
0$
0%
1&
0'
0*
1,
#379
0#
1$
1%
0&
1(
#380
1#
0$
0%
0(
0,
#381
0#
1$
#382
1#
#383
0#
0$
1%
1&
1'
1(
0)
#384
1#
0%
0(
1)
#385
0#
1$
0&
0)
#386
1#
0'
#387
0#
1'
1(
1)
#388
1#
0$
0'
#389
0#
1%
1&
1'
0(
#390
1#
0%
0&
0'
0)
#391
0#
1%
1)
#392
1#
1&
1'
1(
0)
#393
0#
0&
0'
#394
1#
0%
1&
1'
0(
1+
#395
0#
1$
1%
0&
1(
1)
#396
1#
0'
0(
0+
#397
0#
1'
0)
#398
1#
0$
0'
1*
#399
0#
1$
1(
#400
1#
1'
0(
0*
#401
0#
0$
0%
1&
1(
1)
#402
1#
0'
0)
#403
0#
1$
0(
#404
1#
0$
1%
0&
1(
#405
0#
0%
1&
0(
#406
1#
1$
1%
0&
1'
#407
0#
0%
1&
1)
#408
1#
0$
1%
0'
1(
1*
#409
0#
1$
0%
#410
1#
1%
1'
0*
1+
1,
#411
0#
0$
0%
0&
#412
1#
1&
0(
0)
0,
#413
0#
1$
1%
0&
0'
1(
#414
1#
0$
1&
1'
0(
#415
0#
0'
1(
#416
1#
1'
1)
#417
0#
0%
0&
0'
0)
#418
1#
1&
1'
#419
0#
1$
1%
0(
#420
1#
0%
0&
1)
1,
#421
0#
0)
#422
1#
0$
1&
0'
1)
0+
0,
#423
0#
0&
0)
#424
1#
1%
1(
1)
#425
0#
1$
0%
0(
#426
1#
0$
1'
0)
#427
0#
1$
1(
#428
1#
1&
#429
0#
0$
0&
0'
0(
1)
#430
1#
1$
1%
0)
1*
#431
0#
1&
1'
1(
1)
#432
1#
0)
#433
0#
0$
0&
0'
0(
#434
1#
0%
1&
1'
0*
1+
#435
0#
0&
0'
#436
1#
1$
1&
1(
1)
0+
#437
0#
0$
1%
0&
1'
0(
0)
#438
1#
1$
1&
0'
1)
1*
1,
#439
0#
0$
0%
0&
1(
0)
#440
1#
1$
1&
0(
1)
0*
0,
#441
0#
1%
1(
0)
#442
1#
0$
0&
0(
1*
#443
0#
0%
1&
1(
#444
1#
1$
1'
0*
#445
0#
0&
0(
#446
1#
0$
0'
1(
1)
1,
#447
0#
0(
0)
#448
1#
1%
1'
0,
#449
0#
#450
1#
0%
1(
#451
0#
0'
0(
#452
1#
1'
1(
1)
1,
#453
0#
1&
0)
#454
1#
1%
1)
#455
0#
0&
0'
0(
0)
#456
1#
1$
1&
1'
1(
1)
1+
#457
0#
0$
0%
#458
1#
1$
0&
0'
0+
#459
0#
0$
1'
0)
#460
1#
1$
1&
0,
#461
0#
0$
1%
0&
0(
1)
#462
1#
0%
1(
0)
1+
#463
0#
0(
1)
#464
1#
1%
1(
0)
0+
#465
0#
1$
0(
#466
1#
0'
#467
0#
0$
1(
#468
1#
1$
0%
1'
#469
0#
0$
1%
0(
#470
1#
1$
0%
1&
0'
1(
#471
0#
0(
1)
#472
1#
1%
0&
0)
1*
#473
0#
1&
1)
#474
1#
0$
0%
0&
1'
0)
0*
#475
0#
1$
1%
0'
#476
1#
0$
0%
1&
1'
#477
0#
0&
#478
1#
1$
1+
#479
0#
0$
1&
1(
#480
1#
1$
0(
0+
#481
0#
#482
1#
0$
0&
1(
1+
#483
0#
1$
1%
1&
1)
#484
1#
0%
0'
0(
0+
1,
#485
0#
0$
0&
1(
0)
#486
1#
1$
1%
1*
0,
#487
0#
1&
0(
#488
1#
0&
1'
1)
1,
#489
0#
0$
1&
1(
#490
1#
1$
0&
0'
0(
0)
0,
#491
0#
0$
0%
1'
1(
1)
#492
1#
1$
1&
0'
0)
0*
#493
0#
0$
1%
0(
1)
#494
1#
1$
1'
0)
1*
1+
#495
0#
0%
0&
0'
1(
1)
#496
1#
1&
0(
0*
0+
#497
0#
1'
#498
1#
0$
0'
1(
0)
#499
0#
1$
1'
0(
#500
1#
1%
0&
1+
#501
0#
0$
0%
1&
#502
1#
1%
0&
1*
0+
#503
0#
0%
0'
1(
1)
#504
1#
1$
1'
0)
0*
#505
0#
0$
0'
0(
#506
1#
1%
1'
1)
1*
1,
#507
0#
1(
#508
1#
1$
0)
0*
0,
#509
0#
0%
1&
0'
0(
1)
#510
1#
1%
1'
1(
0)
1*
#511
0#
0$
0&
#512
1#
1&
0'
0(
#513
0#
0%
0&
1)
#514
1#
1$
1%
1'
0)
0*
1+
#515
0#
1&
1(
1)
#516
1#
0$
0%
0&
0'
0)
0+
#517
0#
1&
1'
0(
#518
1#
1$
0&
0'
#519
0#
1%
1&
1'
1(
1)
#520
1#
0%
0&
0(
#521
0#
0$
1(
#522
1#
0'
0)
#523
0#
1'
1)
#524
1#
1&
0(
1,
#525
0#
0&
1(
0)
#526
1#
1$
1%
1)
1+
0,
#527
0#
1&
0)
#528
1#
0$
0%
1)
0+
1,
#529
0#
0&
0(
0)
#530
1#
1$
1%
0'
1)
#531
0#
0%
#532
1#
1'
0,
#533
0#
0$
1&
1(
#534
1#
1$
0(
0)
#535
0#
0$
0'
#536
1#
1$
1%
0&
1'
1)
1*
1+
#537
0#
0$
1&
#538
1#
1$
0&
0)
0+
#539
0#
1&
0'
1(
1)
#540
1#
1'
0(
0)
#541
0#
0$
0&
0'
1)
#542
1#
1&
1'
1+
#543
0#
1$
0%
0'
0)
#544
1#
0$
1'
0*
#545
0#
1%
0&
1)
#546
1#
1$
1&
#547
0#
0%
0&
0'
1(
0)
#548
1#
1&
1'
#549
0#
1%
0'
1)
#550
1#
0%
0&
0(
0)
0+
#551
0#
1%
1(
1)
#552
1#
1&
0(
0)
1*
#553
0#
0%
1'
1)
#554
1#
1%
0&
1(
1+
#555
0#
1&
0'
#556
1#
0$
0)
0+
#557
0#
0&
0(
1)
#558
1#
1$
1'
1(
0*
1+
1,
#559
0#
0$
1&
0'
0)
#560
1#
0%
0(
1)
0+
#561
0#
1$
1'
#562
1#
0$
1%
0&
1(
1+
0,
#563
0#
1&
0(
0)
#564
1#
1$
0%
1)
0+
1,
#565
0#
0&
0'
1(
0)
#566
1#
0$
1%
1&
1'
0(
1*
1+
0,
#567
0#
1$
0&
0'
#568
1#
0$
1(
1)
0*
0+
#569
0#
1&
#570
1#
0%
0&
1'
1,
#571
0#
1%
0'
0(
#572
1#
1$
1&
0)
0,
#573
0#
0$
0%
0&
#574
1#
1&
1'
1)
1+
#575
0#
0&
0'
1(
#576
1#
1&
1'
0)
#577
0#
0&
0(
1)
#578
1#
1%
1,
#579
0#
0%
0'
1(
0)
#580
1#
1%
1'
0(
0+
0,
#581
0#
0'
1(
1)
#582
1#
1$
0%
1'
#583
0#
0$
0(
0)
#584
1#
1$
0'
1(
1)
1,
#585
0#
0$
1%
1'
#586
1#
1&
0)
1*
0,
#587
0#
0(
1)
#588
1#
1$
0%
0&
0)
0*
1+
#589
0#
1%
1&
0'
#590
1#
0&
1'
1(
1*
0+
#591
0#
0$
0%
1)
#592
1#
1%
1&
0(
1,
#593
0#
1$
0%
0'
1(
0)
#594
1#
0$
0&
1)
0*
0,
#595
0#
1&
0(
0)
#596
1#
1$
1%
0&
1'
1(
#597
0#
0%
#598
1#
0$
1%
0(
1*
#599
0#
0%
1&
0'
1)
#600
1#
0&
1'
0)
0*
#601
0#
0'
1)
#602
1#
1$
1%
0)
#603
0#
0$
#604
1#
1$
0%
1(
#605
0#
0$
1%
1&
1'
0(
#606
1#
1$
0%
0&
0'
1)
1,
#607
0#
0$
1%
1'
1(
#608
1#
0'
0(
1*
0,
#609
0#
0%
#610
1#
1%
1(
0*
#611
0#
1$
1'
0)
#612
1#
0$
#613
0#
1$
1&
0'
0(
1)
#614
1#
0$
0%
0)
#615
0#
#616
1#
1%
0&
1(
1)
#617
0#
1$
0%
1&
#618
1#
0$
1%
0&
1'
0(
1,
#619
0#
#620
1#
1$
0%
1&
0)
0,
#621
0#
1%
0&
1(
#622
1#
0%
1&
0(
1)
1+
#623
0#
0$
0&
#624
1#
1$
1&
0'
0+
#625
0#
1(
0)
#626
1#
0$
1%
0&
1*
#627
0#
1&
0(
1)
#628
1#
1'
1(
0*
1,
#629
0#
1$
0&
#630
1#
0$
1&
0'
#631
0#
0)
#632
1#
1$
1'
0(
1)
1+
#633
0#
0%
0&
#634
1#
1%
0'
0)
1*
0+
0,
#635
0#
0%
1(
1)
#636
1#
1%
1&
1'
0)
#637
0#
0%
0&
0(
#638
1#
1%
1&
1(
1)
1+
1,
#639
0#
0$
0&
0'
0(
0)
#640
1#
1$
0%
1'
1)
0*
#641
0#
1%
0)
#642
1#
1&
0'
1)
1*
0+
0,
#643
0#
0$
1(
0)
#644
1#
0&
0(
1)
#645
0#
1$
#646
1#
0$
0%
1'
0*
